vrtl/defines.v
`define ZeroWord 16'b0
`define DataWidth 16

vrtl/alu.v
/*   16-bit alu for Hack CPU

The ALU (Arithmetic Logic Unit).
Computes one of the following functions:
x+y, x-y, y-x, 0, 1, -1, x, y, -x, -y, ~x, ~y,
x+1, y+1, x-1, y-1, x&y, x|y on two 16-bit inputs, 
according to 6 input bits denoted zx,nx,zy,ny,f,no.
In addition, the ALU computes two 1-bit outputs:
if the ALU output == 0, zr is set to 1; otherwise zr is set to 0;
if the ALU output < 0, ng is set to 1; otherwise ng is set to 0.

Implementation: the ALU logic manipulates the x and y inputs
and operates on the resulting values, as follows:
ALU(x= ,y= ,zx= ,nx= ,zy= ,ny= ,f= ,no= ,out= ,zr= ,ng= )
if (zx == 1) set x = 0        // 16-bit constant
if (nx == 1) set x = ~x       // bitwise not
if (zy == 1) set y = 0        // 16-bit constant
if (ny == 1) set y = ~y       // bitwise not
if (f == 1)  set out = x + y  // integer 2's complement addition
if (f == 0)  set out = x & y  // bitwise and
if (no == 1) set out = ~out   // bitwise not
if (out == 0) set zr = 1
if (out < 0) set ng = 1

alu u_alu(
    .x_i(),
    .y_i(),
    .zx_i(),
    .nx_i(),
    .zy_i(),
    .ny_i(),
    .f_i(),
    .no_i(),
    .out_o(),
    .zr_o(),
    .ng_o()
);

*/

`include "defines.v"

module alu(
    input wire [`DataWidth-1:0] x_i,
    input wire [`DataWidth-1:0] y_i,
    input wire zx_i,
    input wire nx_i,
    input wire zy_i,
    input wire ny_i,
    input wire f_i,
    input wire no_i,
    output wire [`DataWidth-1:0] out_o,
    output wire zr_o,
    output wire ng_o
);

    wire [`DataWidth-1:0] zx_tmp;
    wire [`DataWidth-1:0] x_tmp;
    wire [`DataWidth-1:0] zy_tmp;
    wire [`DataWidth-1:0] y_tmp;
    wire [`DataWidth-1:0] sum_tmp;
    wire [`DataWidth-1:0] and_tmp;
    wire [`DataWidth-1:0] out_tmp;
    wire [`DataWidth-1:0] out_buf;
    assign out_o = out_buf;

    // deal with zx, nx, get new x : x_tmp
    assign zx_tmp = zx_i ? `ZeroWord : x_i;
    assign x_tmp = nx_i ? ~zx_tmp : zx_tmp;

    // deal with zy, ny, get new y : y_tmp 
    assign zy_tmp = zy_i ? `ZeroWord : y_i;
    assign y_tmp = ny_i ? ~zy_tmp : zy_tmp;

    // deal with f, get x+y or x&y
    assign sum_tmp = x_tmp + y_tmp;
    assign and_tmp = x_tmp & y_tmp;
    assign out_tmp = f_i ? sum_tmp : and_tmp;

    // deal with no, get out_buf
    assign out_buf = no_i ? ~out_tmp : out_tmp;

    // get zr
    assign zr_o = ~(|out_buf);

    // get ng
    assign ng_o = out_buf[15] ? 1'b1 : 1'b0;  

endmodule

vtest/tb/alu_tb.v
`timescale 1ns / 1ps

module alu_tb();
    reg [15:0] in_x;
    reg [15:0] in_y;
    reg z_x;
    reg nx;
    reg z_y;
    reg ny;
    reg f;
    reg no;
    wire [15:0] out;
    wire zr;
    wire ng;

    alu u_alu(
        .x_i(in_x),
        .y_i(in_y),
        .zx_i(z_x),
        .nx_i(nx),
        .zy_i(z_y),
        .ny_i(ny),
        .f_i(f),
        .no_i(no),
        .out_o(out),
        .zr_o(zr),
        .ng_o(ng)
    );

    initial begin
        in_x=16'b0000000000000000;in_y=16'b1111111111111111;
        z_x=0;nx=0;z_y=0;ny=0;f=0;no=0;
        $display("test running...");
        #10 z_x=1;nx=0;z_y=1;ny=0;f=1;no=0;
        #10 z_x=1;nx=1;z_y=1;ny=1;f=1;no=1;
        #10 z_x=1;nx=1;z_y=1;ny=0;f=1;no=0;
        #10 z_x=0;nx=0;z_y=1;ny=1;f=0;no=0;
        #10 z_x=1;nx=1;z_y=0;ny=0;f=0;no=0;
        #10 z_x=0;nx=0;z_y=1;ny=1;f=0;no=1;
        #10 z_x=1;nx=1;z_y=0;ny=0;f=0;no=1;
        #10 z_x=0;nx=0;z_y=1;ny=1;f=1;no=1;
        #10 z_x=1;nx=1;z_y=0;ny=0;f=1;no=1;
        #10 z_x=0;nx=1;z_y=1;ny=1;f=1;no=1;
        #10 z_x=1;nx=1;z_y=0;ny=1;f=1;no=1;
        #10 z_x=0;nx=0;z_y=1;ny=1;f=1;no=0;
        #10 z_x=1;nx=1;z_y=0;ny=0;f=1;no=0;
        #10 z_x=0;nx=0;z_y=0;ny=0;f=1;no=0;
        #10 z_x=0;nx=1;z_y=0;ny=0;f=1;no=1;
        #10 z_x=0;nx=0;z_y=0;ny=1;f=1;no=1;
        #10 z_x=0;nx=0;z_y=0;ny=0;f=0;no=0;
        #10 z_x=0;nx=1;z_y=0;ny=1;f=0;no=1;
        #10 in_x=16'b0000000000010001;in_y=16'b0000000000000011;
        z_x=0;nx=0;z_y=0;ny=0;f=0;no=0;
        #30 z_x=1;nx=0;z_y=1;ny=0;f=1;no=0;
        #10 z_x=1;nx=1;z_y=1;ny=1;f=1;no=1;
        #10 z_x=1;nx=1;z_y=1;ny=0;f=1;no=0;
        #10 z_x=0;nx=0;z_y=1;ny=1;f=0;no=0;
        #10 z_x=1;nx=1;z_y=0;ny=0;f=0;no=0;
        #10 z_x=0;nx=0;z_y=1;ny=1;f=0;no=1;
        #10 z_x=1;nx=1;z_y=0;ny=0;f=0;no=1;
        #10 z_x=0;nx=0;z_y=1;ny=1;f=1;no=1;
        #10 z_x=1;nx=1;z_y=0;ny=0;f=1;no=1;
        #10 z_x=0;nx=1;z_y=1;ny=1;f=1;no=1;
        #10 z_x=1;nx=1;z_y=0;ny=1;f=1;no=1;
        #10 z_x=0;nx=0;z_y=1;ny=1;f=1;no=0;
        #10 z_x=1;nx=1;z_y=0;ny=0;f=1;no=0;
        #10 z_x=0;nx=0;z_y=0;ny=0;f=1;no=0;
        #10 z_x=0;nx=1;z_y=0;ny=0;f=1;no=1;
        #10 z_x=0;nx=0;z_y=0;ny=1;f=1;no=1;
        #10 z_x=0;nx=0;z_y=0;ny=0;f=0;no=0;
        #10 z_x=0;nx=1;z_y=0;ny=1;f=0;no=1;
        #1000 
        $finish;
    end

    initial begin
        $dumpfile("vtest/dumpfile/alu.vcd");
	    $dumpvars(0,alu_tb);
	end

endmodule

// |        x         |        y         |zx |nx |zy |ny | f |no |       out        |zr |ng |
// | 0000000000000000 | 1111111111111111 | 1 | 0 | 1 | 0 | 1 | 0 | 0000000000000000 | 1 | 0 |
// | 0000000000000000 | 1111111111111111 | 1 | 1 | 1 | 1 | 1 | 1 | 0000000000000001 | 0 | 0 |
// | 0000000000000000 | 1111111111111111 | 1 | 1 | 1 | 0 | 1 | 0 | 1111111111111111 | 0 | 1 |
// | 0000000000000000 | 1111111111111111 | 0 | 0 | 1 | 1 | 0 | 0 | 0000000000000000 | 1 | 0 |
// | 0000000000000000 | 1111111111111111 | 1 | 1 | 0 | 0 | 0 | 0 | 1111111111111111 | 0 | 1 |
// | 0000000000000000 | 1111111111111111 | 0 | 0 | 1 | 1 | 0 | 1 | 1111111111111111 | 0 | 1 |
// | 0000000000000000 | 1111111111111111 | 1 | 1 | 0 | 0 | 0 | 1 | 0000000000000000 | 1 | 0 |
// | 0000000000000000 | 1111111111111111 | 0 | 0 | 1 | 1 | 1 | 1 | 0000000000000000 | 1 | 0 |
// | 0000000000000000 | 1111111111111111 | 1 | 1 | 0 | 0 | 1 | 1 | 0000000000000001 | 0 | 0 |
// | 0000000000000000 | 1111111111111111 | 0 | 1 | 1 | 1 | 1 | 1 | 0000000000000001 | 0 | 0 |
// | 0000000000000000 | 1111111111111111 | 1 | 1 | 0 | 1 | 1 | 1 | 0000000000000000 | 1 | 0 |
// | 0000000000000000 | 1111111111111111 | 0 | 0 | 1 | 1 | 1 | 0 | 1111111111111111 | 0 | 1 |
// | 0000000000000000 | 1111111111111111 | 1 | 1 | 0 | 0 | 1 | 0 | 1111111111111110 | 0 | 1 |
// | 0000000000000000 | 1111111111111111 | 0 | 0 | 0 | 0 | 1 | 0 | 1111111111111111 | 0 | 1 |
// | 0000000000000000 | 1111111111111111 | 0 | 1 | 0 | 0 | 1 | 1 | 0000000000000001 | 0 | 0 |
// | 0000000000000000 | 1111111111111111 | 0 | 0 | 0 | 1 | 1 | 1 | 1111111111111111 | 0 | 1 |
// | 0000000000000000 | 1111111111111111 | 0 | 0 | 0 | 0 | 0 | 0 | 0000000000000000 | 1 | 0 |
// | 0000000000000000 | 1111111111111111 | 0 | 1 | 0 | 1 | 0 | 1 | 1111111111111111 | 0 | 1 |
// | 0000000000010001 | 0000000000000011 | 1 | 0 | 1 | 0 | 1 | 0 | 0000000000000000 | 1 | 0 |
// | 0000000000010001 | 0000000000000011 | 1 | 1 | 1 | 1 | 1 | 1 | 0000000000000001 | 0 | 0 |
// | 0000000000010001 | 0000000000000011 | 1 | 1 | 1 | 0 | 1 | 0 | 1111111111111111 | 0 | 1 |
// | 0000000000010001 | 0000000000000011 | 0 | 0 | 1 | 1 | 0 | 0 | 0000000000010001 | 0 | 0 |
// | 0000000000010001 | 0000000000000011 | 1 | 1 | 0 | 0 | 0 | 0 | 0000000000000011 | 0 | 0 |
// | 0000000000010001 | 0000000000000011 | 0 | 0 | 1 | 1 | 0 | 1 | 1111111111101110 | 0 | 1 |
// | 0000000000010001 | 0000000000000011 | 1 | 1 | 0 | 0 | 0 | 1 | 1111111111111100 | 0 | 1 |
// | 0000000000010001 | 0000000000000011 | 0 | 0 | 1 | 1 | 1 | 1 | 1111111111101111 | 0 | 1 |
// | 0000000000010001 | 0000000000000011 | 1 | 1 | 0 | 0 | 1 | 1 | 1111111111111101 | 0 | 1 |
// | 0000000000010001 | 0000000000000011 | 0 | 1 | 1 | 1 | 1 | 1 | 0000000000010010 | 0 | 0 |
// | 0000000000010001 | 0000000000000011 | 1 | 1 | 0 | 1 | 1 | 1 | 0000000000000100 | 0 | 0 |
// | 0000000000010001 | 0000000000000011 | 0 | 0 | 1 | 1 | 1 | 0 | 0000000000010000 | 0 | 0 |
// | 0000000000010001 | 0000000000000011 | 1 | 1 | 0 | 0 | 1 | 0 | 0000000000000010 | 0 | 0 |
// | 0000000000010001 | 0000000000000011 | 0 | 0 | 0 | 0 | 1 | 0 | 0000000000010100 | 0 | 0 |
// | 0000000000010001 | 0000000000000011 | 0 | 1 | 0 | 0 | 1 | 1 | 0000000000001110 | 0 | 0 |
// | 0000000000010001 | 0000000000000011 | 0 | 0 | 0 | 1 | 1 | 1 | 1111111111110010 | 0 | 1 |
// | 0000000000010001 | 0000000000000011 | 0 | 0 | 0 | 0 | 0 | 0 | 0000000000000001 | 0 | 0 |
// | 0000000000010001 | 0000000000000011 | 0 | 1 | 0 | 1 | 0 | 1 | 0000000000010011 | 0 | 0 |

vtest/dumpfile/alu.vcd
$date
	Fri May  5 15:27:05 2023
$end
$version
	Icarus Verilog
$end
$timescale
	1ps
$end
$scope module alu_tb $end
$var wire 1 ! zr $end
$var wire 16 " out [15:0] $end
$var wire 1 # ng $end
$var reg 1 $ f $end
$var reg 16 % in_x [15:0] $end
$var reg 16 & in_y [15:0] $end
$var reg 1 ' no $end
$var reg 1 ( nx $end
$var reg 1 ) ny $end
$var reg 1 * z_x $end
$var reg 1 + z_y $end
$scope module u_alu $end
$var wire 16 , and_tmp [15:0] $end
$var wire 1 $ f_i $end
$var wire 1 ' no_i $end
$var wire 1 ( nx_i $end
$var wire 1 ) ny_i $end
$var wire 16 - out_o [15:0] $end
$var wire 16 . x_i [15:0] $end
$var wire 16 / y_i [15:0] $end
$var wire 1 ! zr_o $end
$var wire 1 * zx_i $end
$var wire 1 + zy_i $end
$var wire 16 0 zy_tmp [15:0] $end
$var wire 16 1 zx_tmp [15:0] $end
$var wire 16 2 y_tmp [15:0] $end
$var wire 16 3 x_tmp [15:0] $end
$var wire 16 4 sum_tmp [15:0] $end
$var wire 16 5 out_tmp [15:0] $end
$var wire 16 6 out_buf [15:0] $end
$var wire 1 # ng_o $end
$upscope $end
$upscope $end
$enddefinitions $end
#0
$dumpvars
b0 6
b0 5
b1111111111111111 4
b0 3
b1111111111111111 2
b0 1
b1111111111111111 0
b1111111111111111 /
b0 .
b0 -
b0 ,
0+
0*
0)
0(
0'
b1111111111111111 &
b0 %
0$
0#
b0 "
1!
$end
#10000
0#
1!
b0 "
b0 -
b0 6
b0 4
b0 2
b0 5
b0 0
1$
1+
1*
#20000
0#
0!
b1111111111111110 5
b1111111111111111 ,
b1 "
b1 -
b1 6
b1111111111111111 2
b1111111111111110 4
b1111111111111111 3
1'
1)
1(
#30000
1#
b1111111111111111 5
b0 ,
b1111111111111111 "
b1111111111111111 -
b1111111111111111 6
b1111111111111111 4
b0 2
0'
0)
#40000
0#
1!
b0 "
b0 -
b0 6
b0 5
b1111111111111111 2
b1111111111111111 4
b0 3
0$
1)
0(
0*
#50000
1#
0!
b1111111111111111 "
b1111111111111111 -
b1111111111111111 6
b1111111111111111 5
b1111111111111111 ,
b1111111111111111 0
b1111111111111110 4
b1111111111111111 3
0)
0+
1(
1*
#60000
1#
b0 5
0!
b0 ,
b1111111111111111 "
b1111111111111111 -
b1111111111111111 6
b1111111111111111 2
b0 0
b1111111111111111 4
b0 3
1'
1)
1+
0(
0*
#70000
0#
1!
b0 "
b0 -
b0 6
b1111111111111111 5
b1111111111111111 ,
b1111111111111111 0
b1111111111111110 4
b1111111111111111 3
0)
0+
1(
1*
#80000
0#
1!
b0 "
b0 -
b0 6
b0 ,
b1111111111111111 5
b1111111111111111 2
b0 0
b1111111111111111 4
b0 3
1$
1)
1+
0(
0*
#90000
0!
b1 "
b1 -
b1 6
b1111111111111110 5
b1111111111111111 ,
b1111111111111111 0
b1111111111111110 4
b1111111111111111 3
0)
0+
1(
1*
#100000
0!
b1 "
b1 -
b1 6
b1111111111111110 5
b1111111111111111 ,
b1111111111111110 4
b1111111111111111 2
b0 0
1)
1+
0*
#110000
1!
b0 "
b0 -
b0 6
b1111111111111111 5
b0 ,
b1111111111111111 4
b0 2
b1111111111111111 0
0+
1*
#120000
1#
b1111111111111111 2
0!
b1111111111111111 5
b1111111111111111 "
b1111111111111111 -
b1111111111111111 6
b0 0
b1111111111111111 4
b0 3
0'
1+
0(
0*
#130000
b1111111111111110 "
b1111111111111110 -
b1111111111111110 6
b1111111111111110 5
b1111111111111111 ,
b1111111111111111 0
b1111111111111110 4
b1111111111111111 3
0)
0+
1(
1*
#140000
b1111111111111111 "
b1111111111111111 -
b1111111111111111 6
b1111111111111111 5
b0 ,
b1111111111111111 4
b0 3
0(
0*
#150000
0#
0!
b1111111111111110 5
b1111111111111111 ,
b1 "
b1 -
b1 6
b1111111111111110 4
b1111111111111111 3
1'
1(
#160000
1#
b1111111111111111 "
b1111111111111111 -
b1111111111111111 6
b0 5
b0 ,
b0 2
b0 4
b0 3
1)
0(
#170000
0#
1!
b0 "
b0 -
b0 6
b1111111111111111 4
b1111111111111111 2
0'
0$
0)
#180000
1#
0!
b1111111111111111 "
b1111111111111111 -
b1111111111111111 6
b0 2
b1111111111111111 4
b1111111111111111 3
1'
1)
1(
#190000
0#
b1 5
0!
b1 ,
b1 "
b1 -
b1 6
b11 2
b10100 4
b10001 3
b11 0
b10001 1
0'
0)
0(
b11 &
b11 /
b10001 %
b10001 .
#220000
1!
b0 ,
b0 "
b0 -
b0 6
b0 2
b0 4
b0 3
b0 5
b0 0
b0 1
1$
1+
1*
#230000
0#
0!
b1111111111111110 5
b1111111111111111 ,
b1 "
b1 -
b1 6
b1111111111111111 2
b1111111111111110 4
b1111111111111111 3
1'
1)
1(
#240000
1#
b1111111111111111 5
b0 ,
b1111111111111111 "
b1111111111111111 -
b1111111111111111 6
b1111111111111111 4
b0 2
0'
0)
#250000
0#
0!
b10001 "
b10001 -
b10001 6
b10001 ,
b10001 5
b1111111111111111 2
b10000 4
b10001 3
b10001 1
0$
1)
0(
0*
#260000
b11 "
b11 -
b11 6
b11 5
b11 ,
b11 2
b11 0
b10 4
b1111111111111111 3
b0 1
0)
0+
1(
1*
#270000
1#
b10001 5
b10001 ,
b1111111111101110 "
b1111111111101110 -
b1111111111101110 6
b1111111111111111 2
b0 0
b10000 4
b10001 3
b10001 1
1'
1)
1+
0(
0*
#280000
b1111111111111100 "
b1111111111111100 -
b1111111111111100 6
b11 5
b11 ,
b11 2
b11 0
b10 4
b1111111111111111 3
b0 1
0)
0+
1(
1*
#290000
b1111111111101111 "
b1111111111101111 -
b1111111111101111 6
b10001 ,
b10000 5
b1111111111111111 2
b0 0
b10000 4
b10001 3
b10001 1
1$
1)
1+
0(
0*
#300000
1#
b1111111111111101 "
b1111111111111101 -
b1111111111111101 6
b10 5
b11 ,
b11 2
b11 0
b10 4
b1111111111111111 3
b0 1
0)
0+
1(
1*
#310000
0#
b10010 "
b10010 -
b10010 6
b1111111111101110 3
b1111111111101101 5
b1111111111101110 ,
b1111111111101101 4
b1111111111111111 2
b0 0
b10001 1
1)
1+
0*
#320000
b100 "
b100 -
b100 6
b1111111111111011 5
b1111111111111100 ,
b1111111111111100 2
b1111111111111011 4
b1111111111111111 3
b11 0
b0 1
0+
1*
#330000
0#
b1111111111111111 2
b10000 5
b10001 ,
b10000 "
b10000 -
b10000 6
b0 0
b10000 4
b10001 3
b10001 1
0'
1+
0(
0*
#340000
0#
b10 "
b10 -
b10 6
b10 5
b11 ,
b11 2
b11 0
b10 4
b1111111111111111 3
b0 1
0)
0+
1(
1*
#350000
b10100 "
b10100 -
b10100 6
b10100 5
b1 ,
b10100 4
b10001 3
b10001 1
0(
0*
#360000
0#
b1111111111110001 5
b10 ,
b1110 "
b1110 -
b1110 6
b1111111111110001 4
b1111111111101110 3
1'
1(
#370000
1#
b1111111111110010 "
b1111111111110010 -
b1111111111110010 6
b1101 5
b10000 ,
b1111111111111100 2
b1101 4
b10001 3
1)
0(
#380000
0#
b1 ,
b1 "
b1 -
b1 6
b1 5
b10100 4
b11 2
0'
0$
0)
#390000
0#
b1111111111101100 5
b1111111111101100 ,
b10011 "
b10011 -
b10011 6
b1111111111111100 2
b1111111111101010 4
b1111111111101110 3
1'
1)
1(
