vrtl/DFF.v
/*  Data flip-flop gate

DFF u_DFF(
    .clk_i(),
    .in_i(),
    .out_o()
);

*/



module DFF(
    input wire clk_i,
    input wire in_i,
    output reg out_o
);
    always @(posedge clk_i) begin
        out_o <= in_i;
    end

endmodule

vrtl/Bit.v
/*  1-bit register

Bit u_Bit(
    .clk_i(),
    .in_i(),
    .load_i(),
    .out_o()
);

*/



module Bit(
    input wire clk_i,
    input wire in_i,
    input wire load_i,
    output wire out_o
);

    wire in_new = load_i ? in_i : out_o;
    
    DFF u_DFF(
        .clk_i(clk_i),
        .in_i(in_new),
        .out_o(out_o)
    );

endmodule

vtest/tb/Bit_tb.v
`timescale 1ns / 1ps

module Bit_tb();

    reg clk;
    reg din;
    reg load;
    wire dout;

    Bit u_Bit(
        .clk_i(clk),
        .in_i(din),
        .load_i(load),
        .out_o(dout)
    );

    always #5 clk = ~clk;

    initial begin
        clk = 1'b0; din = 1'b0; load = 1'b1;
        $display("test running...");
        #3 din = 1'b1;
        #3 din = 1'b1;
        #3 din = 1'b1;
        #3 din = 1'b0;
        #3 din = 1'b0;
        #3 din = 1'b0;
        #3 din = 1'b0;
        #3 din = 1'b1;
        #3 din = 1'b1;
        #3 din = 1'b1;
        #3 din = 1'b1;
        #3 din = 1'b0;
        #3 din = 1'b1;
        #3 din = 1'b0;
        #3 din = 1'b1;
        #3 din = 1'b0;
        #3 din = 1'b1; load = 1'b0;
        #3 din = 1'b1;
        #3 din = 1'b1;
        #3 din = 1'b0;
        #3 din = 1'b0;
        #3 din = 1'b0;
        #3 din = 1'b0;
        #3 din = 1'b1; load = 1'b1;
        #3 din = 1'b1;
        #3 din = 1'b1;
        #3 din = 1'b1;
        #3 din = 1'b0;
        #3 din = 1'b1;
        #3 din = 1'b0; 
        #3 din = 1'b1;
        #3 din = 1'b0;
        #1000 
        $finish;
    end

    initial begin
        $dumpfile("vtest/dumpfile/Bit.vcd");
	    $dumpvars(0,Bit_tb);
	end

endmodule

vtest/dumpfile/Bit.vcd
$date
	Tue May  2 18:23:21 2023
$end
$version
	Icarus Verilog
$end
$timescale
	1ps
$end
$scope module Bit_tb $end
$var wire 1 ! dout $end
$var reg 1 " clk $end
$var reg 1 # din $end
$var reg 1 $ load $end
$scope module u_Bit $end
$var wire 1 " clk_i $end
$var wire 1 # in_i $end
$var wire 1 $ load_i $end
$var wire 1 ! out_o $end
$var wire 1 % in_new $end
$scope module u_DFF $end
$var wire 1 " clk_i $end
$var wire 1 % in_i $end
$var reg 1 ! out_o $end
$upscope $end
$upscope $end
$upscope $end
$enddefinitions $end
#0
$dumpvars
0%
1$
0#
0"
x!
$end
#3000
1%
1#
#5000
1!
1"
#10000
0"
#12000
0%
0#
#15000
0!
1"
#20000
0"
#24000
1%
1#
#25000
1!
1"
#30000
0"
#35000
1"
#36000
0%
0#
#39000
1%
1#
#40000
0"
#42000
0%
0#
#45000
0!
1%
1#
1"
#48000
0%
0#
#50000
0"
#51000
0$
1#
#55000
1"
#60000
0#
0"
#65000
1"
#70000
0"
#72000
1%
1$
1#
#75000
1!
1"
#80000
0"
#84000
0%
0#
#85000
0!
1"
#87000
1%
1#
#90000
0%
0#
0"
#93000
1%
1#
#95000
1!
1"
#96000
0%
0#
#100000
0"
#105000
0!
1"
