vrtl/defines.v
`define ZeroWord 16'b0
`define PCResetAddr 16'b0
`define DataWidth 16
`define InstWidth 16

`define InstAddrWidth 15
`define InstDepth 32768

`define DataAddrWidth 15
`define DataDepth 32768

vrtl/Register.v
/*  16-bit register

Register u_Register(
    .clk_i(),
    .in_i(),
    .load_i(),
    .out_o()
);

*/

module Register #(parameter WIDTH = 1, parameter RESET_VAL = 0) (
    input wire clk_i,
    input wire reset_i,
    input wire [WIDTH-1:0] in_i,
    input wire load_i,
    output reg [WIDTH-1:0] out_o
);
  always @ (posedge clk_i) begin
    if (reset_i) out_o <= RESET_VAL;
    else if (load_i) out_o <= in_i;
  end
endmodule

vrtl/pc.v
/* Program Counter

 * A 16-bit counter with load and reset control bits.
 * if      (reset[t] == 1) out[t+1] = 0
 * else if (load[t] == 1)  out[t+1] = in[t]
 * else if (inc[t] == 1)   out[t+1] = out[t] + 1  (integer addition)
 * else                    out[t+1] = out[t]

    pc u_pc(
        .clk_i(),
        .in_i(),
        .load_i(),
        .inc_i(),
        .reset_i(),
        .out_o()
    );


 */

`include "defines.v"

 module pc(
    input wire clk_i,
    input wire [`DataWidth-1:0] in_i,
    input wire load_i,
    input wire inc_i,
    input wire reset_i,
    output wire [`DataWidth-1:0] out_o
);

    wire [`DataWidth-1:0] in_inc;
    wire [`DataWidth-1:0] in_tmp1;
    wire [`DataWidth-1:0] in_tmp2;
    wire [`DataWidth-1:0] in_new;
    wire [`DataWidth-1:0] out_buf;
    assign out_o = out_buf;

    assign in_inc = out_buf + 1'b1; // pc+1
    assign in_tmp1 = inc_i ? in_inc : out_buf; // +1 or hold
    assign in_tmp2 = load_i ? in_i : in_tmp1;  // load or (+1 or hold)

    register #(.WIDTH(`DataWidth), .RESET_VAL(`PCResetAddr)) u_pc_register(
        .clk_i(clk_i),
        .in_i(in_tmp2),
        .reset_i(reset_i),
        .load_i(1'b1),
        .out_o(out_buf)
    );


endmodule

vrtl/alu.v
/*   16-bit alu for Hack CPU

The ALU (Arithmetic Logic Unit).Computes one of the following functions:
x+y, x-y, y-x, 0, 1, -1, x, y, -x, -y, ~x, ~y, x+1, y+1, x-1, y-1, x&y, x|y on two 16-bit inputs, 
according to 6 input bits denoted zx,nx,zy,ny,f,no. In addition, the ALU computes two 1-bit outputs:
if the ALU output == 0, zr is set to 1; otherwise zr is set to 0;
if the ALU output < 0, ng is set to 1; otherwise ng is set to 0.

Implementation: the ALU logic manipulates the x and y inputs
and operates on the resulting values, as follows:
ALU(x= ,y= ,zx= ,nx= ,zy= ,ny= ,f= ,no= ,out= ,zr= ,ng= )
if (zx == 1) set x = 0        // 16-bit constant
if (nx == 1) set x = ~x       // bitwise not
if (zy == 1) set y = 0        // 16-bit constant
if (ny == 1) set y = ~y       // bitwise not
if (f == 1)  set out = x + y  // integer 2's complement addition
if (f == 0)  set out = x & y  // bitwise and
if (no == 1) set out = ~out   // bitwise not
if (out == 0) set zr = 1
if (out < 0) set ng = 1

    alu u_alu(
        .x_i(),
        .y_i(),
        .zx_i(),
        .nx_i(),
        .zy_i(),
        .ny_i(),
        .f_i(),
        .no_i(),
        .out_o(),
        .zr_o(),
        .ng_o()
    );

*/

`include "defines.v"

module alu(
    input wire [`DataWidth-1:0] x_i,
    input wire [`DataWidth-1:0] y_i,
    input wire zx_i,
    input wire nx_i,
    input wire zy_i,
    input wire ny_i,
    input wire f_i,
    input wire no_i,
    output wire [`DataWidth-1:0] out_o,
    output wire zr_o,
    output wire ng_o
);

    wire [`DataWidth-1:0] zx_tmp;
    wire [`DataWidth-1:0] x_tmp;
    wire [`DataWidth-1:0] zy_tmp;
    wire [`DataWidth-1:0] y_tmp;
    wire [`DataWidth-1:0] sum_tmp;
    wire [`DataWidth-1:0] and_tmp;
    wire [`DataWidth-1:0] out_tmp;
    wire [`DataWidth-1:0] out_buf;
    assign out_o = out_buf;

    // deal with zx, nx, get new x : x_tmp
    assign zx_tmp = zx_i ? `ZeroWord : x_i;
    assign x_tmp = nx_i ? ~zx_tmp : zx_tmp;

    // deal with zy, ny, get new y : y_tmp 
    assign zy_tmp = zy_i ? `ZeroWord : y_i;
    assign y_tmp = ny_i ? ~zy_tmp : zy_tmp;

    // deal with f, get x+y or x&y
    assign sum_tmp = x_tmp + y_tmp;
    assign and_tmp = x_tmp & y_tmp;
    assign out_tmp = f_i ? sum_tmp : and_tmp;

    // deal with no, get out_buf
    assign out_buf = no_i ? ~out_tmp : out_tmp;

    // get zr
    assign zr_o = ~(|out_buf);

    // get ng
    assign ng_o = out_buf[15] ? 1'b1 : 1'b0;  

endmodule

vrtl/CPU.v
/* CPU

CPU u_CPU(
    .clk_i(),
    .reset_i(),
    .data_i(),
    .inst_i(),
    .data_o(),
    .dmem_wr_en_o(),
    .dmem_addr_o(),
    .pc_o()
);


 */

`include "defines.v"

 module CPU(
    input wire clk_i,
    input wire reset_i,
    input wire [15:0] data_i,
    input wire [15:0] inst_i,
    output wire [15:0] data_o,
    output wire dmem_wr_en_o,
    output wire [14:0] dmem_addr_o,
    output wire [14:0] pc_o

);
    wire d1;
    wire d2;
    wire d3;
    wire j1;
    wire j2;
    wire j3;
    wire [15:0] alu_out_buf;
    wire [15:0] a_reg_in;
    wire [15:0] a_reg_out;
    wire [15:0] x_alu;
    wire [15:0] y_alu;
    wire ng_alu;
    wire zr_alu;
    wire jump;
    wire [15:0] pc_buf;
    assign d1 = inst_i[15] & inst_i[5];
    assign d2 = inst_i[15] & inst_i[4];
    assign d3 = inst_i[15] & inst_i[3];
    assign j1 = inst_i[15] & inst_i[2];
    assign j2 = inst_i[15] & inst_i[1];
    assign j3 = inst_i[15] & inst_i[0];
    assign dmem_wr_en_o = d3;
    assign data_o = alu_out_buf;
    assign a_reg_load = (~inst_i[15]) | d1;
    assign dmem_addr_o = a_reg_out[14:0]; // get addressM
    assign jump = (j1 & ng_alu) | (j2 & zr_alu) | (j3 & (~ng_alu) & (~zr_alu));  // get jump 
    assign pc_o = pc_buf[14:0];
    assign a_reg_in = inst_i[15] ? alu_out_buf : inst_i; // choose AReg input
    assign y_alu = inst_i[12] ? data_i : a_reg_out; // choose ALU input
    

    alu u_alu(
        .x_i(x_alu), .y_i(y_alu),
        .zx_i(inst_i[11]), .nx_i(inst_i[10]), .zy_i(inst_i[9]), .ny_i(inst_i[8]),
        .f_i(inst_i[7]), .no_i(inst_i[6]), .out_o(alu_out_buf), .zr_o(zr_alu), .ng_o(ng_alu)
    );

    // A-Register
    register #(.WIDTH(`DataWidth), .RESET_VAL(`ZeroWord)) u_Aregister(
        .clk_i(clk_i),
        .in_i(a_reg_in),
        .reset_i(reset),
        .load_i(a_reg_load),
        .out_o(a_reg_out)
    );

    // D-Register
    register #(.WIDTH(`DataWidth), .RESET_VAL(`ZeroWord)) u_Dregister(
        .clk_i(clk_i),
        .in_i(alu_out_buf),
        .reset_i(reset),
        .load_i(d2),
        .out_o(x_alu)
    );
    
    pc u_pc(
        .clk_i(clk_i), 
        .in_i(a_reg_out), 
        .load_i(jump), 
        .inc_i(~jump), 
        .reset_i(reset_i), 
        .out_o(pc_buf)
    );

endmodule

vrtl/rom.v
module rom(
    input wire [14:0] addr_i,    // addr
    output wire [15:0] data_o     // read data
    );

    // 32K rom (32768)
    reg [15:0] _rom [0:32768-1];
    assign data_o = _rom[addr_i];


endmodule

vrtl/ram.v
/* ram

ram u_ram(
    .clk_i(),
    .reset_i(),
    .load_i(),
    .addr_i(),
    .data_i(),
    .data_o()
);

*/


module ram(

    input wire clk_i,
    input wire reset_i,
    input wire load_i,           // write enable
    input wire [14:0] addr_i,    // addr
    input wire [15:0] data_i,
    output wire [15:0] data_o         // read data

    );

    // 32K(32768) ram 
    reg [15:0] _ram [0:32768-1];


    always @ (posedge clk_i) begin
        if (load_i == 1'b1) begin
            _ram[addr_i] <= data_i;
        end
    end

    assign data_o = reset_i ? 16'b0 : _ram[addr_i];

endmodule

vrtl/Computer.v
module Computer(
    input wire clk,
    input wire reset
);

    wire [14:0] pc;
    wire [15:0] instruction;
    wire dmem_en;
    wire [14:0] dmem_addr;
    wire [15:0] data_out;
    wire [15:0] data_in;

    ram u_ram(
        .clk_i(clk), 
        .reset_i(reset), 
        .load_i(dmem_en), 
        .addr_i(dmem_addr), 
        .data_i(data_out), 
        .data_o(data_in)
    );

    rom u_rom(
        .addr_i(pc), 
        .data_o(instruction)
    );

    CPU u_CPU(
        .clk_i(clk),
        .reset_i(reset),
        .data_i(data_in),
        .inst_i(instruction),
        .data_o(data_out),
        .dmem_wr_en_o(dmem_en),
        .dmem_addr_o(dmem_addr),
        .pc_o(pc)
    );

endmodule

vtest/tb/Computer_tb.v
`timescale 1ns / 1ps

module Computer_tb();

    reg clk;
    reg rst;

    Computer u_Computer(
        .clk(clk),
        .reset(rst)
    );

    always #5 clk = ~clk;

    initial begin
        clk = 1'b0; rst = 1'b1;
        $display("test running...");
        #50 rst = 1'b0; u_Computer.u_ram._ram[0] = 16'd2; u_Computer.u_ram._ram[1] = 16'd3; 
        #500 rst = 1'b1;
        #50 rst = 1'b0; u_Computer.u_ram._ram[0] = 16'd566; u_Computer.u_ram._ram[1] = 16'd3; 
        #500 rst = 1'b1;
        #50 rst = 1'b0; u_Computer.u_ram._ram[0] = 16'd5; u_Computer.u_ram._ram[1] = 16'd5; 
        #500 rst = 1'b1;
        #100
        $finish;
    end

    initial begin
        $readmemb("vtest/hack_program/Max.hack", u_Computer.u_rom._rom);
    end

    initial begin
        $dumpfile("vtest/dumpfile/Computer.vcd");
	    $dumpvars(0,Computer_tb);
	end

endmodule

vtest/dumpfile/Computer.vcd
$date
	Fri May  5 16:04:53 2023
$end
$version
	Icarus Verilog
$end
$timescale
	1ps
$end
$scope module Computer_tb $end
$var reg 1 ! clk $end
$var reg 1 " rst $end
$scope module u_Computer $end
$var wire 1 ! clk $end
$var wire 1 " reset $end
$var wire 15 # pc [14:0] $end
$var wire 16 $ instruction [15:0] $end
$var wire 1 % dmem_en $end
$var wire 15 & dmem_addr [14:0] $end
$var wire 16 ' data_out [15:0] $end
$var wire 16 ( data_in [15:0] $end
$scope module u_CPU $end
$var wire 1 ) a_reg_load $end
$var wire 1 ! clk_i $end
$var wire 1 * d1 $end
$var wire 1 + d2 $end
$var wire 1 , d3 $end
$var wire 16 - data_o [15:0] $end
$var wire 1 % dmem_wr_en_o $end
$var wire 1 . j1 $end
$var wire 1 / j2 $end
$var wire 1 0 j3 $end
$var wire 1 1 jump $end
$var wire 1 2 reset $end
$var wire 1 " reset_i $end
$var wire 1 3 zr_alu $end
$var wire 16 4 y_alu [15:0] $end
$var wire 16 5 x_alu [15:0] $end
$var wire 15 6 pc_o [14:0] $end
$var wire 16 7 pc_buf [15:0] $end
$var wire 1 8 ng_alu $end
$var wire 16 9 inst_i [15:0] $end
$var wire 15 : dmem_addr_o [14:0] $end
$var wire 16 ; data_i [15:0] $end
$var wire 16 < alu_out_buf [15:0] $end
$var wire 16 = a_reg_out [15:0] $end
$var wire 16 > a_reg_in [15:0] $end
$scope module u_Aregister $end
$var wire 1 ! clk_i $end
$var wire 16 ? in_i [15:0] $end
$var wire 1 ) load_i $end
$var wire 1 2 reset_i $end
$var reg 16 @ out_o [15:0] $end
$upscope $end
$scope module u_Dregister $end
$var wire 1 ! clk_i $end
$var wire 1 + load_i $end
$var wire 1 2 reset_i $end
$var wire 16 A in_i [15:0] $end
$var reg 16 B out_o [15:0] $end
$upscope $end
$scope module u_alu $end
$var wire 16 C and_tmp [15:0] $end
$var wire 1 D f_i $end
$var wire 1 E no_i $end
$var wire 1 F nx_i $end
$var wire 1 G ny_i $end
$var wire 16 H out_o [15:0] $end
$var wire 16 I x_i [15:0] $end
$var wire 16 J y_i [15:0] $end
$var wire 1 3 zr_o $end
$var wire 1 K zx_i $end
$var wire 1 L zy_i $end
$var wire 16 M zy_tmp [15:0] $end
$var wire 16 N zx_tmp [15:0] $end
$var wire 16 O y_tmp [15:0] $end
$var wire 16 P x_tmp [15:0] $end
$var wire 16 Q sum_tmp [15:0] $end
$var wire 16 R out_tmp [15:0] $end
$var wire 16 S out_buf [15:0] $end
$var wire 1 8 ng_o $end
$upscope $end
$scope module u_pc $end
$var wire 1 ! clk_i $end
$var wire 16 T in_i [15:0] $end
$var wire 1 U inc_i $end
$var wire 1 1 load_i $end
$var wire 16 V out_o [15:0] $end
$var wire 1 " reset_i $end
$var wire 16 W out_buf [15:0] $end
$var wire 16 X in_tmp2 [15:0] $end
$var wire 16 Y in_tmp1 [15:0] $end
$var wire 16 Z in_inc [15:0] $end
$scope module u_pc_register $end
$var wire 1 ! clk_i $end
$var wire 16 [ in_i [15:0] $end
$var wire 1 \ load_i $end
$var wire 1 " reset_i $end
$var reg 16 ] out_o [15:0] $end
$upscope $end
$upscope $end
$upscope $end
$scope module u_ram $end
$var wire 15 ^ addr_i [14:0] $end
$var wire 1 ! clk_i $end
$var wire 16 _ data_i [15:0] $end
$var wire 1 % load_i $end
$var wire 1 " reset_i $end
$var wire 16 ` data_o [15:0] $end
$upscope $end
$scope module u_rom $end
$var wire 15 a addr_i [14:0] $end
$var wire 16 b data_o [15:0] $end
$upscope $end
$upscope $end
$upscope $end
$enddefinitions $end
#0
$dumpvars
bx b
bx a
b0 `
bx _
bx ^
bx ]
1\
bx [
bx Z
bx Y
bx X
bx W
bx V
xU
bx T
bx S
bx R
bx Q
bx P
bx O
bx N
bx M
xL
xK
bx J
bx I
bx H
xG
xF
xE
xD
bx C
bx B
bx A
bx @
bx ?
bx >
bx =
bx <
b0 ;
bx :
bx 9
x8
bx 7
bx 6
bx 5
bx 4
x3
z2
x1
x0
x/
x.
bx -
x,
x+
x*
x)
b0 (
bx '
bx &
x%
bx $
bx #
1"
0!
$end
#5000
1U
b1 X
b1 [
01
1)
00
0/
0.
0%
0,
0+
0*
0E
0D
0G
0L
0F
0K
b0 >
b0 ?
b1 Y
b0 $
b0 9
b0 b
b0 #
b0 6
b0 a
b1 Z
b0 7
b0 V
b0 W
b0 ]
1!
#10000
0!
#15000
08
13
b0 '
b0 -
b0 _
b0 <
b0 A
b0 H
b0 S
b0 R
b0 C
b0 O
b0 M
b0 4
b0 J
b0 &
b0 :
b0 ^
b0 =
b0 @
b0 T
1!
#20000
0!
#25000
1!
#30000
0!
#35000
1!
#40000
0!
#45000
1!
#50000
b10 (
b10 ;
b10 `
0!
0"
#55000
03
b10 >
b10 ?
b10 '
b10 -
b10 _
b10 <
b10 A
b10 H
b10 S
b10 R
b10 C
b1 Q
b1111111111111111 P
b10 O
b10 M
0)
b0 N
b10 4
b10 J
1+
b10 X
b10 [
1F
1K
b10 Y
b1111110000010000 $
b1111110000010000 9
b1111110000010000 b
b1 #
b1 6
b1 a
b10 Z
b1 7
b1 V
b1 W
b1 ]
1!
#60000
0!
#65000
13
b0 '
b0 -
b0 _
b0 <
b0 A
b0 H
b0 S
b0 R
b0 C
b0 O
b0 M
1)
b10 Q
b10 P
b10 N
b0 4
b0 J
b1 >
b1 ?
0+
b11 X
b11 [
0F
0K
b11 Y
b1 $
b1 9
b1 b
b10 #
b10 6
b10 a
b10 5
b10 B
b10 I
b11 Z
b10 7
b10 V
b10 W
b10 ]
1!
#70000
0!
#75000
18
03
0)
b1 C
b1111111111111111 '
b1111111111111111 -
b1111111111111111 _
b1111111111111111 <
b1111111111111111 A
b1111111111111111 H
b1111111111111111 S
b0 R
b1111111111111101 P
1+
b0 Q
b11 O
b100 X
b100 [
1E
1D
1F
b1111111111111111 >
b1111111111111111 ?
b11 M
b11 (
b11 ;
b11 `
b100 Y
b1111010011010000 $
b1111010011010000 9
b1111010011010000 b
b11 #
b11 6
b11 a
b11 4
b11 J
b1 &
b1 :
b1 ^
b100 Z
b11 7
b11 V
b11 W
b11 ]
b1 =
b1 @
b1 T
1!
#80000
0!
#85000
08
b1 O
b1 C
b1 M
1)
b1 '
b1 -
b1 _
b1 <
b1 A
b1 H
b1 S
b1 R
b0 Q
b1111111111111111 P
b1 4
b1 J
b1010 >
b1010 ?
0+
b101 X
b101 [
0E
0D
0F
b1111111111111111 N
b101 Y
b1010 $
b1010 9
b1010 b
b100 #
b100 6
b100 a
b1111111111111111 5
b1111111111111111 B
b1111111111111111 I
b101 Z
b100 7
b100 V
b100 W
b100 ]
1!
#90000
0!
#95000
18
1U
01
b1111111111111111 '
b1111111111111111 -
b1111111111111111 _
b1111111111111111 <
b1111111111111111 A
b1111111111111111 H
b1111111111111111 S
b1111111111111111 R
0)
b1111111111111111 C
10
b1111111111111110 Q
b1111111111111111 O
b110 X
b110 [
1G
1L
b1111111111111111 >
b1111111111111111 ?
b0 M
bx (
bx ;
bx `
b110 Y
b1110001100000001 $
b1110001100000001 9
b1110001100000001 b
b101 #
b101 6
b101 a
b1010 4
b1010 J
b1010 &
b1010 :
b1010 ^
b110 Z
b101 7
b101 V
b101 W
b101 ]
b1010 =
b1010 @
b1010 T
1!
#100000
0!
#105000
08
b1010 '
b1010 -
b1010 _
b1010 <
b1010 A
b1010 H
b1010 S
b1010 R
b1010 C
1)
b1001 Q
b1010 O
b1010 M
b1 >
b1 ?
00
b111 X
b111 [
0G
0L
b111 Y
b1 $
b1 9
b1 b
b110 #
b110 6
b110 a
b111 Z
b110 7
b110 V
b110 W
b110 ]
1!
#110000
0!
#115000
03
b11 '
b11 -
b11 _
b11 <
b11 A
b11 H
b11 S
b11 R
0)
b11 C
b1111111111111111 P
b0 N
1+
b10 Q
b11 O
b1000 X
b1000 [
1F
1K
b11 >
b11 ?
b11 M
b11 (
b11 ;
b11 `
b1000 Y
b1111110000010000 $
b1111110000010000 9
b1111110000010000 b
b111 #
b111 6
b111 a
b11 4
b11 J
b1 &
b1 :
b1 ^
b1000 Z
b111 7
b111 V
b111 W
b111 ]
b1 =
b1 @
b1 T
1!
#120000
0!
#125000
b1 '
b1 -
b1 _
b1 <
b1 A
b1 H
b1 S
b1 R
b1 C
b1 O
b1 M
1)
b100 Q
b11 P
b11 N
b1 4
b1 J
b1100 >
b1100 ?
0+
b1001 X
b1001 [
0F
0K
b1001 Y
b1100 $
b1100 9
b1100 b
b1000 #
b1000 6
b1000 a
b11 5
b11 B
b11 I
b1001 Z
b1000 7
b1000 V
b1000 W
b1000 ]
1!
#130000
0!
#135000
13
0U
11
b0 '
b0 -
b0 _
b0 <
b0 A
b0 H
b0 S
b0 P
0)
b0 C
b0 R
b0 N
10
1/
1.
b0 Q
b0 O
b1100 X
b1100 [
1D
1L
1K
b0 >
b0 ?
b0 M
bx (
bx ;
bx `
b1001 Y
b1110101010000111 $
b1110101010000111 9
b1110101010000111 b
b1001 #
b1001 6
b1001 a
b1100 4
b1100 J
b1100 &
b1100 :
b1100 ^
b1010 Z
b1001 7
b1001 V
b1001 W
b1001 ]
b1100 =
b1100 @
b1100 T
1!
#140000
0!
#145000
b1101 X
b1101 [
1U
01
b1100 O
b1111 Q
b11 P
1)
b1100 M
b11 N
b10 >
b10 ?
00
0/
0.
0D
0L
0K
b1101 Y
b10 $
b10 9
b10 b
b1100 #
b1100 6
b1100 a
b1101 Z
b1100 7
b1100 V
b1100 W
b1100 ]
1!
#150000
0!
#155000
03
b11 '
b11 -
b11 _
b11 <
b11 A
b11 H
b11 S
b11 R
0)
b11 C
1%
1,
b10 Q
b1111111111111111 O
b1110 X
b1110 [
1G
1L
b11 >
b11 ?
b0 M
b1110 Y
b1110001100001000 $
b1110001100001000 9
b1110001100001000 b
b1101 #
b1101 6
b1101 a
b10 4
b10 J
b10 &
b10 :
b10 ^
b1110 Z
b1101 7
b1101 V
b1101 W
b1101 ]
b10 =
b10 @
b10 T
1!
#160000
0!
#165000
b10 '
b10 -
b10 _
b10 <
b10 A
b10 H
b10 S
b10 R
b10 C
1)
b101 Q
b10 O
b10 M
b1110 >
b1110 ?
0%
0,
b1111 X
b1111 [
0G
0L
b11 (
b11 ;
b11 `
b1111 Y
b1110 $
b1110 9
b1110 b
b1110 #
b1110 6
b1110 a
b1111 Z
b1110 7
b1110 V
b1110 W
b1110 ]
1!
#170000
0!
#175000
13
0U
11
b0 C
b0 '
b0 -
b0 _
b0 <
b0 A
b0 H
b0 S
b0 P
0)
b0 R
b0 N
10
1/
1.
b0 Q
b0 O
b1110 X
b1110 [
1D
1L
1K
b0 >
b0 ?
b0 M
bx (
bx ;
bx `
b1111 Y
b1110101010000111 $
b1110101010000111 9
b1110101010000111 b
b1111 #
b1111 6
b1111 a
b1110 4
b1110 J
b1110 &
b1110 :
b1110 ^
b10000 Z
b1111 7
b1111 V
b1111 W
b1111 ]
b1110 =
b1110 @
b1110 T
1!
#180000
0!
#185000
b1111 X
b1111 [
03
b10 '
b10 -
b10 _
b10 <
b10 A
b10 H
b10 S
1U
b10 R
01
b10 C
b1110 O
b10001 Q
b11 P
1)
b1110 M
b11 N
b1110 >
b1110 ?
00
0/
0.
0D
0L
0K
b1111 Y
b1110 $
b1110 9
b1110 b
b1110 #
b1110 6
b1110 a
b1111 Z
b1110 7
b1110 V
b1110 W
b1110 ]
1!
#190000
0!
#195000
13
0U
11
b0 C
b0 '
b0 -
b0 _
b0 <
b0 A
b0 H
b0 S
b0 O
b0 Q
b0 P
0)
b0 R
b0 M
b0 N
10
1/
1.
b1110 X
b1110 [
1D
1L
1K
b0 >
b0 ?
b1111 Y
b1110101010000111 $
b1110101010000111 9
b1110101010000111 b
b1111 #
b1111 6
b1111 a
b10000 Z
b1111 7
b1111 V
b1111 W
b1111 ]
1!
#200000
0!
#205000
b1111 X
b1111 [
03
b10 '
b10 -
b10 _
b10 <
b10 A
b10 H
b10 S
1U
b10 R
01
b10 C
b1110 O
b10001 Q
b11 P
1)
b1110 M
b11 N
b1110 >
b1110 ?
00
0/
0.
0D
0L
0K
b1111 Y
b1110 $
b1110 9
b1110 b
b1110 #
b1110 6
b1110 a
b1111 Z
b1110 7
b1110 V
b1110 W
b1110 ]
1!
#210000
0!
#215000
13
0U
11
b0 C
b0 '
b0 -
b0 _
b0 <
b0 A
b0 H
b0 S
b0 O
b0 Q
b0 P
0)
b0 R
b0 M
b0 N
10
1/
1.
b1110 X
b1110 [
1D
1L
1K
b0 >
b0 ?
b1111 Y
b1110101010000111 $
b1110101010000111 9
b1110101010000111 b
b1111 #
b1111 6
b1111 a
b10000 Z
b1111 7
b1111 V
b1111 W
b1111 ]
1!
#220000
0!
#225000
b1111 X
b1111 [
03
b10 '
b10 -
b10 _
b10 <
b10 A
b10 H
b10 S
1U
b10 R
01
b10 C
b1110 O
b10001 Q
b11 P
1)
b1110 M
b11 N
b1110 >
b1110 ?
00
0/
0.
0D
0L
0K
b1111 Y
b1110 $
b1110 9
b1110 b
b1110 #
b1110 6
b1110 a
b1111 Z
b1110 7
b1110 V
b1110 W
b1110 ]
1!
#230000
0!
#235000
13
0U
11
b0 C
b0 '
b0 -
b0 _
b0 <
b0 A
b0 H
b0 S
b0 O
b0 Q
b0 P
0)
b0 R
b0 M
b0 N
10
1/
1.
b1110 X
b1110 [
1D
1L
1K
b0 >
b0 ?
b1111 Y
b1110101010000111 $
b1110101010000111 9
b1110101010000111 b
b1111 #
b1111 6
b1111 a
b10000 Z
b1111 7
b1111 V
b1111 W
b1111 ]
1!
#240000
0!
#245000
b1111 X
b1111 [
03
b10 '
b10 -
b10 _
b10 <
b10 A
b10 H
b10 S
1U
b10 R
01
b10 C
b1110 O
b10001 Q
b11 P
1)
b1110 M
b11 N
b1110 >
b1110 ?
00
0/
0.
0D
0L
0K
b1111 Y
b1110 $
b1110 9
b1110 b
b1110 #
b1110 6
b1110 a
b1111 Z
b1110 7
b1110 V
b1110 W
b1110 ]
1!
#250000
0!
#255000
13
0U
11
b0 C
b0 '
b0 -
b0 _
b0 <
b0 A
b0 H
b0 S
b0 O
b0 Q
b0 P
0)
b0 R
b0 M
b0 N
10
1/
1.
b1110 X
b1110 [
1D
1L
1K
b0 >
b0 ?
b1111 Y
b1110101010000111 $
b1110101010000111 9
b1110101010000111 b
b1111 #
b1111 6
b1111 a
b10000 Z
b1111 7
b1111 V
b1111 W
b1111 ]
1!
#260000
0!
#265000
b1111 X
b1111 [
03
b10 '
b10 -
b10 _
b10 <
b10 A
b10 H
b10 S
1U
b10 R
01
b10 C
b1110 O
b10001 Q
b11 P
1)
b1110 M
b11 N
b1110 >
b1110 ?
00
0/
0.
0D
0L
0K
b1111 Y
b1110 $
b1110 9
b1110 b
b1110 #
b1110 6
b1110 a
b1111 Z
b1110 7
b1110 V
b1110 W
b1110 ]
1!
#270000
0!
#275000
13
0U
11
b0 C
b0 '
b0 -
b0 _
b0 <
b0 A
b0 H
b0 S
b0 O
b0 Q
b0 P
0)
b0 R
b0 M
b0 N
10
1/
1.
b1110 X
b1110 [
1D
1L
1K
b0 >
b0 ?
b1111 Y
b1110101010000111 $
b1110101010000111 9
b1110101010000111 b
b1111 #
b1111 6
b1111 a
b10000 Z
b1111 7
b1111 V
b1111 W
b1111 ]
1!
#280000
0!
#285000
b1111 X
b1111 [
03
b10 '
b10 -
b10 _
b10 <
b10 A
b10 H
b10 S
1U
b10 R
01
b10 C
b1110 O
b10001 Q
b11 P
1)
b1110 M
b11 N
b1110 >
b1110 ?
00
0/
0.
0D
0L
0K
b1111 Y
b1110 $
b1110 9
b1110 b
b1110 #
b1110 6
b1110 a
b1111 Z
b1110 7
b1110 V
b1110 W
b1110 ]
1!
#290000
0!
#295000
13
0U
11
b0 C
b0 '
b0 -
b0 _
b0 <
b0 A
b0 H
b0 S
b0 O
b0 Q
b0 P
0)
b0 R
b0 M
b0 N
10
1/
1.
b1110 X
b1110 [
1D
1L
1K
b0 >
b0 ?
b1111 Y
b1110101010000111 $
b1110101010000111 9
b1110101010000111 b
b1111 #
b1111 6
b1111 a
b10000 Z
b1111 7
b1111 V
b1111 W
b1111 ]
1!
#300000
0!
#305000
b1111 X
b1111 [
03
b10 '
b10 -
b10 _
b10 <
b10 A
b10 H
b10 S
1U
b10 R
01
b10 C
b1110 O
b10001 Q
b11 P
1)
b1110 M
b11 N
b1110 >
b1110 ?
00
0/
0.
0D
0L
0K
b1111 Y
b1110 $
b1110 9
b1110 b
b1110 #
b1110 6
b1110 a
b1111 Z
b1110 7
b1110 V
b1110 W
b1110 ]
1!
#310000
0!
#315000
13
0U
11
b0 C
b0 '
b0 -
b0 _
b0 <
b0 A
b0 H
b0 S
b0 O
b0 Q
b0 P
0)
b0 R
b0 M
b0 N
10
1/
1.
b1110 X
b1110 [
1D
1L
1K
b0 >
b0 ?
b1111 Y
b1110101010000111 $
b1110101010000111 9
b1110101010000111 b
b1111 #
b1111 6
b1111 a
b10000 Z
b1111 7
b1111 V
b1111 W
b1111 ]
1!
#320000
0!
#325000
b1111 X
b1111 [
03
b10 '
b10 -
b10 _
b10 <
b10 A
b10 H
b10 S
1U
b10 R
01
b10 C
b1110 O
b10001 Q
b11 P
1)
b1110 M
b11 N
b1110 >
b1110 ?
00
0/
0.
0D
0L
0K
b1111 Y
b1110 $
b1110 9
b1110 b
b1110 #
b1110 6
b1110 a
b1111 Z
b1110 7
b1110 V
b1110 W
b1110 ]
1!
#330000
0!
#335000
13
0U
11
b0 C
b0 '
b0 -
b0 _
b0 <
b0 A
b0 H
b0 S
b0 O
b0 Q
b0 P
0)
b0 R
b0 M
b0 N
10
1/
1.
b1110 X
b1110 [
1D
1L
1K
b0 >
b0 ?
b1111 Y
b1110101010000111 $
b1110101010000111 9
b1110101010000111 b
b1111 #
b1111 6
b1111 a
b10000 Z
b1111 7
b1111 V
b1111 W
b1111 ]
1!
#340000
0!
#345000
b1111 X
b1111 [
03
b10 '
b10 -
b10 _
b10 <
b10 A
b10 H
b10 S
1U
b10 R
01
b10 C
b1110 O
b10001 Q
b11 P
1)
b1110 M
b11 N
b1110 >
b1110 ?
00
0/
0.
0D
0L
0K
b1111 Y
b1110 $
b1110 9
b1110 b
b1110 #
b1110 6
b1110 a
b1111 Z
b1110 7
b1110 V
b1110 W
b1110 ]
1!
#350000
0!
#355000
13
0U
11
b0 C
b0 '
b0 -
b0 _
b0 <
b0 A
b0 H
b0 S
b0 O
b0 Q
b0 P
0)
b0 R
b0 M
b0 N
10
1/
1.
b1110 X
b1110 [
1D
1L
1K
b0 >
b0 ?
b1111 Y
b1110101010000111 $
b1110101010000111 9
b1110101010000111 b
b1111 #
b1111 6
b1111 a
b10000 Z
b1111 7
b1111 V
b1111 W
b1111 ]
1!
#360000
0!
#365000
b1111 X
b1111 [
03
b10 '
b10 -
b10 _
b10 <
b10 A
b10 H
b10 S
1U
b10 R
01
b10 C
b1110 O
b10001 Q
b11 P
1)
b1110 M
b11 N
b1110 >
b1110 ?
00
0/
0.
0D
0L
0K
b1111 Y
b1110 $
b1110 9
b1110 b
b1110 #
b1110 6
b1110 a
b1111 Z
b1110 7
b1110 V
b1110 W
b1110 ]
1!
#370000
0!
#375000
13
0U
11
b0 C
b0 '
b0 -
b0 _
b0 <
b0 A
b0 H
b0 S
b0 O
b0 Q
b0 P
0)
b0 R
b0 M
b0 N
10
1/
1.
b1110 X
b1110 [
1D
1L
1K
b0 >
b0 ?
b1111 Y
b1110101010000111 $
b1110101010000111 9
b1110101010000111 b
b1111 #
b1111 6
b1111 a
b10000 Z
b1111 7
b1111 V
b1111 W
b1111 ]
1!
#380000
0!
#385000
b1111 X
b1111 [
03
b10 '
b10 -
b10 _
b10 <
b10 A
b10 H
b10 S
1U
b10 R
01
b10 C
b1110 O
b10001 Q
b11 P
1)
b1110 M
b11 N
b1110 >
b1110 ?
00
0/
0.
0D
0L
0K
b1111 Y
b1110 $
b1110 9
b1110 b
b1110 #
b1110 6
b1110 a
b1111 Z
b1110 7
b1110 V
b1110 W
b1110 ]
1!
#390000
0!
