vrtl/DFF.v
/*  Data flip-flop gate

DFF u_DFF(
    .clk_i(),
    .in_i(),
    .out_o()
);

*/



module DFF(
    input wire clk_i,
    input wire in_i,
    output reg out_o
);
    always @(posedge clk_i) begin
        out_o <= in_i;
    end

endmodule

vtest/DFF_tb.v
`timescale 1ns / 1ps

module DFF_tb();

    reg clk;
    reg din;
    wire dout;

    DFF u_DFF(
        .clk_i(clk),
        .in_i(din),
        .out_o(dout)
    );

    always #5 clk = ~clk;

    initial begin
        clk = 1'b0;din = 1'b0;
        $display("test running...");
        #3 din = 1'b1;
        #3 din = 1'b1;
        #3 din = 1'b1;
        #3 din = 1'b0;
        #3 din = 1'b0;
        #3 din = 1'b0;
        #3 din = 1'b0;
        #3 din = 1'b1;
        #3 din = 1'b1;
        #3 din = 1'b1;
        #3 din = 1'b1;
        #3 din = 1'b0;
        #3 din = 1'b1;
        #3 din = 1'b0;
        #3 din = 1'b1;
        #3 din = 1'b0;
        #1000 
        $finish;
    end

    initial begin
        $dumpfile("vtest/dumpfile/DFF.vcd");
	    $dumpvars(0,DFF_tb);
	end

endmodule

vtest/dumpfile/DFF.vcd
$date
	Tue May  2 18:16:05 2023
$end
$version
	Icarus Verilog
$end
$timescale
	1ps
$end
$scope module DFF_tb $end
$var wire 1 ! dout $end
$var reg 1 " clk $end
$var reg 1 # din $end
$scope module u_DFF $end
$var wire 1 " clk_i $end
$var wire 1 # in_i $end
$var reg 1 ! out_o $end
$upscope $end
$upscope $end
$enddefinitions $end
#0
$dumpvars
0#
0"
x!
$end
#3000
1#
#5000
1!
1"
#10000
0"
#12000
0#
#15000
0!
1"
#20000
0"
#24000
1#
#25000
1!
1"
#30000
0"
#35000
1"
#36000
0#
#39000
1#
#40000
0"
#42000
0#
#45000
1#
1"
#48000
0#
#50000
0"
#55000
0!
1"
