vrtl/DMux4Way.v
/*  DMux4Way

* 4-way demultiplexor:
* {a, b, c, d} = {in, 0, 0, 0} if sel == 00
*                {0, in, 0, 0} if sel == 01
*                {0, 0, in, 0} if sel == 10
*                {0, 0, 0, in} if sel == 11

DMux4Way u_DMux4Way(
    .in_i(),
    .sel_i(),
    .a_o(),
    .b_o(),
    .c_o(),
    .d_o()
);

*/

module DMux4Way(
    input wire in_i,
    input wire [1:0] sel_i,
    output wire a_o,
    output wire b_o,
    output wire c_o,
    output wire d_o
);
    assign a_o = sel_i[0] ? 1'b0 : (sel_i[1] ? 1'b0 : in_i);
    assign b_o = sel_i[0] ? (sel_i[1] ? 1'b0 : in_i) : 1'b0;
    assign c_o = sel_i[0] ? 1'b0 : (sel_i[1] ? in_i : 1'b0);
    assign d_o = sel_i[0] ? (sel_i[1] ? in_i : 1'b0) : 1'b0;

endmodule

vtest/tb/DMux4Way_tb.v
`timescale 1ns / 1ps

module DMux4Way_tb();

    reg in;
    reg [1:0] sel;
    wire a;
    wire b;
    wire c;
    wire d;

    DMux4Way u_DMux4Way(
        .in_i(in),
        .sel_i(sel),
        .a_o(a),
        .b_o(b),
        .c_o(c),
        .d_o(d)
    );

    initial begin
        in = 0;
        sel = 2'b00;
        $display("test running...");
        #10 
        in = 0;sel = 2'b00;
        #10 
        in = 0;sel = 2'b01;
        #10 
        in = 0;sel = 2'b10;
        #10 
        in = 0;sel = 2'b11;
        #10 
        in = 1;sel = 2'b00;
        #10 
        in = 1;sel = 2'b01;
        #10 
        in = 1;sel = 2'b10;
        #10 
        in = 1;sel = 2'b11;
        #1000 
        $finish;
    end

    initial begin
        $dumpfile("vtest/dumpfile/DMux4Way.vcd");
	    $dumpvars(0,DMux4Way_tb);
	end

endmodule

vtest/dumpfile/DMux4Way.vcd
$date
	Mon May  1 13:24:31 2023
$end
$version
	Icarus Verilog
$end
$timescale
	1ps
$end
$scope module DMux4Way_tb $end
$var wire 1 ! d $end
$var wire 1 " c $end
$var wire 1 # b $end
$var wire 1 $ a $end
$var reg 1 % in $end
$var reg 2 & sel [1:0] $end
$scope module u_DMux4Way $end
$var wire 1 % in_i $end
$var wire 2 ' sel_i [1:0] $end
$var wire 1 ! d_o $end
$var wire 1 " c_o $end
$var wire 1 # b_o $end
$var wire 1 $ a_o $end
$upscope $end
$upscope $end
$enddefinitions $end
#0
$dumpvars
b0 '
b0 &
0%
0$
0#
0"
0!
$end
#20000
b1 &
b1 '
#30000
b10 &
b10 '
#40000
b11 &
b11 '
#50000
1$
b0 &
b0 '
1%
#60000
0$
1#
b1 &
b1 '
#70000
0#
1"
b10 &
b10 '
#80000
0"
1!
b11 &
b11 '
