vrtl/DMux4Way.v
/*  DMux4Way

* 4-way demultiplexor:
* {a, b, c, d} = {in, 0, 0, 0} if sel == 00
*                {0, in, 0, 0} if sel == 01
*                {0, 0, in, 0} if sel == 10
*                {0, 0, 0, in} if sel == 11

DMux4Way u_DMux4Way(
    .in_i(),
    .sel_i(),
    .a_o(),
    .b_o(),
    .c_o(),
    .d_o()
);

*/

module DMux4Way(
    input wire in_i,
    input wire [1:0] sel_i,
    output wire a_o,
    output wire b_o,
    output wire c_o,
    output wire d_o
);
    assign a_o = sel_i[0] ? 1'b0 : (sel_i[1] ? 1'b0 : in_i);
    assign b_o = sel_i[0] ? (sel_i[1] ? 1'b0 : in_i) : 1'b0;
    assign c_o = sel_i[0] ? 1'b0 : (sel_i[1] ? in_i : 1'b0);
    assign d_o = sel_i[0] ? (sel_i[1] ? in_i : 1'b0) : 1'b0;

endmodule

vrtl/DMux.v
/*  DMux
 * Demultiplexor:
 * {a, b} = {in, 0} if sel == 0
 *          {0, in} if sel == 1

DMux u_DMux(
    .in_i(),
    .sel_i(),
    .a_o(),
    .b_o()
);

*/

module DMux(
    input wire in_i,
    input wire sel_i,
    output wire a_o,
    output wire b_o
);
    assign a_o = sel_i ? 1'b0 : in_i;
    assign b_o = sel_i ? in_i : 1'b0;

endmodule

vrtl/DMux8Way.v
/*  DMux8Way

 * 8-way demultiplexor:
 * {a, b, c, d, e, f, g, h} = {in, 0, 0, 0, 0, 0, 0, 0} if sel == 000
 *                            {0, in, 0, 0, 0, 0, 0, 0} if sel == 001
 *                            etc.
 *                            {0, 0, 0, 0, 0, 0, 0, in} if sel == 111

DMux8Way u_DMux8Way(
    .in_i(),
    .sel_i(),
    .a_o(),
    .b_o(),
    .c_o(),
    .d_o(),
    .e_o(),
    .f_o(),
    .g_o(),
    .h_o()
);

*/

`include "./DMux.v"
`include "./DMux4Way.v"

module DMux8Way(
    input wire in_i,
    input wire [2:0] sel_i,
    output wire a_o,
    output wire b_o,
    output wire c_o,
    output wire d_o,
    output wire e_o,
    output wire f_o,
    output wire g_o,
    output wire h_o
);

    wire tmp1;
    wire tmp2;

    DMux u_DMux(
        .in_i(in_i),
        .sel_i(sel_i[2]),
        .a_o(tmp1),
        .b_o(tmp2)
    );

    DMux4Way u1_DMux4Way(
        .in_i(tmp1),
        .sel_i(sel_i[1:0]),
        .a_o(a_o),
        .b_o(b_o),
        .c_o(c_o),
        .d_o(d_o)
    );

    DMux4Way u2_DMux4Way(
        .in_i(tmp2),
        .sel_i(sel_i[1:0]),
        .a_o(e_o),
        .b_o(f_o),
        .c_o(g_o),
        .d_o(h_o)
    );

endmodule

vtest/tb/DMux8Way_tb.v
`timescale 1ns / 1ps

module DMux8Way_tb();

    reg in;
    reg [2:0] sel;
    wire a;
    wire b;
    wire c;
    wire d;
    wire e;
    wire f;
    wire g;
    wire h;

    DMux8Way u_DMux8Way(
        .in_i(in),
        .sel_i(sel),
        .a_o(a),
        .b_o(b),
        .c_o(c),
        .d_o(d),
        .e_o(e),
        .f_o(f),
        .g_o(g),
        .h_o(h)
    );

    initial begin
        in = 0;
        sel = 3'b000;
        $display("test running...");
        #10 in = 0;sel = 3'b000;
        #10 sel = 3'b001;
        #10 sel = 3'b010;
        #10 sel = 3'b011;
        #10 sel = 3'b100;
        #10 sel = 3'b101;
        #10 sel = 3'b110;
        #10 sel = 3'b111;
        #10 in = 1;sel = 3'b000;
        #10 sel = 3'b001;
        #10 sel = 3'b010;
        #10 sel = 3'b011;
        #10 sel = 3'b100;
        #10 sel = 3'b101;
        #10 sel = 3'b110;
        #10 sel = 3'b111;
        #1000 
        $finish;
    end

    initial begin
        $dumpfile("vtest/dumpfile/DMux8Way.vcd");
	    $dumpvars(0,DMux8Way_tb);
	end

endmodule

vtest/dumpfile/DMux8Way.vcd
$date
	Mon May  1 13:38:05 2023
$end
$version
	Icarus Verilog
$end
$timescale
	1ps
$end
$scope module DMux8Way_tb $end
$var wire 1 ! h $end
$var wire 1 " g $end
$var wire 1 # f $end
$var wire 1 $ e $end
$var wire 1 % d $end
$var wire 1 & c $end
$var wire 1 ' b $end
$var wire 1 ( a $end
$var reg 1 ) in $end
$var reg 3 * sel [2:0] $end
$scope module u_DMux8Way $end
$var wire 1 ) in_i $end
$var wire 3 + sel_i [2:0] $end
$var wire 1 , tmp2 $end
$var wire 1 - tmp1 $end
$var wire 1 ! h_o $end
$var wire 1 " g_o $end
$var wire 1 # f_o $end
$var wire 1 $ e_o $end
$var wire 1 % d_o $end
$var wire 1 & c_o $end
$var wire 1 ' b_o $end
$var wire 1 ( a_o $end
$scope module u1_DMux4Way $end
$var wire 2 . sel_i [1:0] $end
$var wire 1 - in_i $end
$var wire 1 % d_o $end
$var wire 1 & c_o $end
$var wire 1 ' b_o $end
$var wire 1 ( a_o $end
$upscope $end
$scope module u2_DMux4Way $end
$var wire 2 / sel_i [1:0] $end
$var wire 1 , in_i $end
$var wire 1 ! d_o $end
$var wire 1 " c_o $end
$var wire 1 # b_o $end
$var wire 1 $ a_o $end
$upscope $end
$scope module u_DMux $end
$var wire 1 ) in_i $end
$var wire 1 0 sel_i $end
$var wire 1 , b_o $end
$var wire 1 - a_o $end
$upscope $end
$upscope $end
$upscope $end
$enddefinitions $end
#0
$dumpvars
00
b0 /
b0 .
0-
0,
b0 +
b0 *
0)
0(
0'
0&
0%
0$
0#
0"
0!
$end
#20000
b1 .
b1 /
b1 *
b1 +
#30000
b10 .
b10 /
b10 *
b10 +
#40000
b11 .
b11 /
b11 *
b11 +
#50000
10
b0 .
b0 /
b100 *
b100 +
#60000
b1 .
b1 /
b101 *
b101 +
#70000
b10 .
b10 /
b110 *
b110 +
#80000
b11 .
b11 /
b111 *
b111 +
#90000
1(
1-
00
b0 .
b0 /
0,
b0 *
b0 +
1)
#100000
0(
1'
b1 .
b1 /
b1 *
b1 +
#110000
0'
1&
b10 .
b10 /
b10 *
b10 +
#120000
0&
1%
b11 .
b11 /
b11 *
b11 +
#130000
0%
1$
0-
1,
10
b0 .
b0 /
b100 *
b100 +
#140000
0$
1#
b1 .
b1 /
b101 *
b101 +
#150000
0#
1"
b10 .
b10 /
b110 *
b110 +
#160000
0"
1!
b11 .
b11 /
b111 *
b111 +
