vrtl/Or.v
/*  Or gate

Or u_Or(
    .a_i(),
    .b_i(),
    .out_o()
);

*/

module Or(
    input wire a_i,
    input wire b_i,
    output wire out_o
);
    assign out_o = a_i | b_i;

endmodule

vrtl/And.v
/*  And gate

And u_And(
    .a_i(),
    .b_i(),
    .out_o()
);

*/

module And(
    input wire a_i,
    input wire b_i,
    output wire out_o
);
    assign out_o = a_i & b_i;

endmodule

vrtl/Xor.v
/*  Xor gate

Xor u_Xor(
    .a_i(),
    .b_i(),
    .out_o()
);

*/

module Xor(
    input wire a_i,
    input wire b_i,
    output wire out_o
);
    assign out_o = a_i ^ b_i;

endmodule

vrtl/HalfAdder.v
/*  Computes the sum of two bits.

HalfAdder u_HalfAdder(
    .a_i(),
    .b_i(),
    .sum_o(),
    .carry_o()
);

*/


module HalfAdder(
    input wire a_i,
    input wire b_i,
    output wire sum_o,
    output wire carry_o
);

    Xor u_Xor(
        .a_i(a_i),
        .b_i(b_i),
        .out_o(sum_o)
    );
    
    And u_And(
        .a_i(a_i),
        .b_i(b_i),
        .out_o(carry_o)
    );

endmodule

vrtl/FullAdder.v
/*  Computes the sum of three bits.

FullAdder u_FullAdder(
    .a_i(),
    .b_i(),
    .c_i(),
    .sum_o(),
    .carry_o()
);

*/

`include "./HalfAdder.v"
`include "./Or.v"

module FullAdder(
    input wire a_i,
    input wire b_i,
    input wire c_i,
    output wire sum_o,
    output wire carry_o
);

    wire tmp_sum;
    wire tmp_carry1;
    wire tmp_carry2;

    HalfAdder u1_HalfAdder(
        .a_i(a_i),
        .b_i(b_i),
        .sum_o(tmp_sum),
        .carry_o(tmp_carry1)
    );

    HalfAdder u2_HalfAdder(
        .a_i(c_i),
        .b_i(tmp_sum),
        .sum_o(sum_o),
        .carry_o(tmp_carry2)
    );
    
    Or u_Or(
        .a_i(tmp_carry1),
        .b_i(tmp_carry2),
        .out_o(carry_o)
    );

endmodule

vtest/FullAdder_tb.v
`timescale 1ns / 1ps

module FullAdder_tb();

    reg a;
    reg b;
    reg c;
    wire sum;
    wire carry;

    FullAdder u_FullAdder(
        .a_i(a),
        .b_i(b),
        .c_i(c),
        .sum_o(sum),
        .carry_o(carry)
    );


    initial begin
        a = 0;b = 0;c = 0;
        $display("test running...");
        #10 a = 0;b = 0;c = 0;
        #10 a = 0;b = 0;c = 1;
        #10 a = 0;b = 1;c = 0;
        #10 a = 0;b = 1;c = 1;
        #10 a = 1;b = 0;c = 0;
        #10 a = 1;b = 0;c = 1;
        #10 a = 1;b = 1;c = 0;
        #10 a = 1;b = 1;c = 1;
        #1000 
        $finish;
    end

    initial begin
        $dumpfile("vtest/dumpfile/FullAdder.vcd");
	    $dumpvars(0,FullAdder_tb);
	end

endmodule

vtest/dumpfile/FullAdder.vcd
$date
	Mon May  1 14:06:28 2023
$end
$version
	Icarus Verilog
$end
$timescale
	1ps
$end
$scope module FullAdder_tb $end
$var wire 1 ! sum $end
$var wire 1 " carry $end
$var reg 1 # a $end
$var reg 1 $ b $end
$var reg 1 % c $end
$scope module u_FullAdder $end
$var wire 1 # a_i $end
$var wire 1 $ b_i $end
$var wire 1 % c_i $end
$var wire 1 & tmp_sum $end
$var wire 1 ' tmp_carry2 $end
$var wire 1 ( tmp_carry1 $end
$var wire 1 ! sum_o $end
$var wire 1 " carry_o $end
$scope module u1_HalfAdder $end
$var wire 1 # a_i $end
$var wire 1 $ b_i $end
$var wire 1 & sum_o $end
$var wire 1 ( carry_o $end
$scope module u_And $end
$var wire 1 # a_i $end
$var wire 1 $ b_i $end
$var wire 1 ( out_o $end
$upscope $end
$scope module u_Xor $end
$var wire 1 # a_i $end
$var wire 1 $ b_i $end
$var wire 1 & out_o $end
$upscope $end
$upscope $end
$scope module u2_HalfAdder $end
$var wire 1 % a_i $end
$var wire 1 & b_i $end
$var wire 1 ! sum_o $end
$var wire 1 ' carry_o $end
$scope module u_And $end
$var wire 1 % a_i $end
$var wire 1 & b_i $end
$var wire 1 ' out_o $end
$upscope $end
$scope module u_Xor $end
$var wire 1 % a_i $end
$var wire 1 & b_i $end
$var wire 1 ! out_o $end
$upscope $end
$upscope $end
$scope module u_Or $end
$var wire 1 ( a_i $end
$var wire 1 ' b_i $end
$var wire 1 " out_o $end
$upscope $end
$upscope $end
$upscope $end
$enddefinitions $end
#0
$dumpvars
0(
0'
0&
0%
0$
0#
0"
0!
$end
#20000
1!
1%
#30000
1&
0%
1$
#40000
1"
1'
0!
1%
#50000
0"
0'
1!
0%
0$
1#
#60000
1"
1'
0!
1%
#70000
0'
1(
0&
0%
1$
#80000
1!
1%
