vrtl/Mux.v
/*  Mux

Mux u_Mux(
    .a_i(),
    .b_i(),
    .sel_i(),
    .out_o()
);

*/

module Mux(
    input wire a_i,
    input wire b_i,
    input wire sel_i,
    output wire out_o
);
    assign out_o = sel_i ? b_i : a_i;

endmodule

vtest/Mux_tb.v
`timescale 1ns / 1ps

module Mux_tb();

    reg a;
    reg b;
    reg sel;
    wire out;

    Mux u_Mux(
        .a_i(a),
        .b_i(b),
        .sel_i(sel),
        .out_o(out)
    );


    initial begin
        a = 0;
        b = 0;
        sel = 0;
        $display("test running...");
        #10 
        a = 0;b = 0;sel = 0;
        #10 
        a = 0;b = 1;sel = 0;
        #10 
        a = 1;b = 0;sel = 0;
        #10 
        a = 1;b = 1;sel = 0;
        #10 
        a = 0;b = 0;sel = 1;
        #10 
        a = 0;b = 1;sel = 1;
        #10 
        a = 1;b = 0;sel = 1;
        #10 
        a = 1;b = 1;sel = 1;
        #1000 
        $finish;
    end

    initial begin
        $dumpfile("vtest/dumpfile/Mux.vcd");
	    $dumpvars(0,Mux_tb);
	end

endmodule

vtest/dumpfile/Mux.vcd
$date
	Mon May  1 00:28:18 2023
$end
$version
	Icarus Verilog
$end
$timescale
	1ps
$end
$scope module Mux_tb $end
$var wire 1 ! out $end
$var reg 1 " a $end
$var reg 1 # b $end
$var reg 1 $ sel $end
$scope module u_Mux $end
$var wire 1 " a_i $end
$var wire 1 # b_i $end
$var wire 1 $ sel_i $end
$var wire 1 ! out_o $end
$upscope $end
$upscope $end
$enddefinitions $end
#0
$dumpvars
0$
0#
0"
0!
$end
#20000
1#
#30000
1!
0#
1"
#40000
1#
#50000
0!
1$
0#
0"
#60000
1!
1#
#70000
0!
0#
1"
#80000
1!
1#
