vrtl/Mux16.v
/*  Mux16: 16-bit Mux

Mux16 u_Mux16(
    .a_i(),
    .b_i(),
    .sel_i(),
    .out_o()
);

*/

module Mux16(
    input wire [15:0] a_i,
    input wire [15:0] b_i,
    input wire sel_i,
    output wire [15:0] out_o
);
    assign out_o = sel_i ? b_i : a_i;

endmodule

vtest/tb/Mux16_tb.v
`timescale 1ns / 1ps

module Mux16_tb();

    reg [15:0] a;
    reg [15:0] b;
    reg sel;
    wire [15:0] out;

    Mux16 u_Mux16(
        .a_i(a),
        .b_i(b),
        .sel_i(sel),
        .out_o(out)
    );

    initial begin
        a = 16'b0000_0000_0000_0000;
        b = 16'b0000_0000_0000_0000;sel = 1'b0;
        $display("test running...");
        #10
        a = 16'b0000_0000_0000_0000;
        b = 16'b0000_0000_0000_0000;sel = 1'b0;
        #10 
        a = 16'b1111_1111_1111_1111;
        b = 16'b0000_0000_0000_0000;sel = 1'b0;
        #10 
        a = 16'b0000_0000_0000_0000;
        b = 16'b1111_1111_1111_1111;sel = 1'b0;
        #10 
        a = 16'b1111_1111_1111_1111;
        b = 16'b1111_1111_1111_1111;sel = 1'b0;
        #10 
        a = 16'b1010_1010_1010_1010;
        b = 16'b0011_1011_1111_0001;sel = 1'b0;
        #10
        a = 16'b0000_0000_0000_0000;
        b = 16'b0000_0000_0000_0000;sel = 1'b1;
        #10 
        a = 16'b1111_1111_1111_1111;
        b = 16'b0000_0000_0000_0000;sel = 1'b1;
        #10 
        a = 16'b0000_0000_0000_0000;
        b = 16'b1111_1111_1111_1111;sel = 1'b1;
        #10 
        a = 16'b1111_1111_1111_1111;
        b = 16'b1111_1111_1111_1111;sel = 1'b1;
        #10 
        a = 16'b1010_1010_1010_1010;
        b = 16'b0011_1011_1111_0001;sel = 1'b1;
        #1000 
        $finish;
    end

    initial begin
        $dumpfile("vtest/dumpfile/Mux16.vcd");
	    $dumpvars(0,Mux16_tb);
	end

endmodule

vtest/dumpfile/Mux16.vcd
$date
	Mon May  1 01:28:18 2023
$end
$version
	Icarus Verilog
$end
$timescale
	1ps
$end
$scope module Mux16_tb $end
$var wire 16 ! out [15:0] $end
$var reg 16 " a [15:0] $end
$var reg 16 # b [15:0] $end
$var reg 1 $ sel $end
$scope module u_Mux16 $end
$var wire 16 % a_i [15:0] $end
$var wire 16 & b_i [15:0] $end
$var wire 1 $ sel_i $end
$var wire 16 ' out_o [15:0] $end
$upscope $end
$upscope $end
$enddefinitions $end
#0
$dumpvars
b0 '
b0 &
b0 %
0$
b0 #
b0 "
b0 !
$end
#20000
b1111111111111111 !
b1111111111111111 '
b1111111111111111 "
b1111111111111111 %
#30000
b0 !
b0 '
b1111111111111111 #
b1111111111111111 &
b0 "
b0 %
#40000
b1111111111111111 !
b1111111111111111 '
b1111111111111111 "
b1111111111111111 %
#50000
b1010101010101010 !
b1010101010101010 '
b11101111110001 #
b11101111110001 &
b1010101010101010 "
b1010101010101010 %
#60000
b0 !
b0 '
1$
b0 #
b0 &
b0 "
b0 %
#70000
b1111111111111111 "
b1111111111111111 %
#80000
b1111111111111111 !
b1111111111111111 '
b1111111111111111 #
b1111111111111111 &
b0 "
b0 %
#90000
b1111111111111111 "
b1111111111111111 %
#100000
b11101111110001 !
b11101111110001 '
b11101111110001 #
b11101111110001 &
b1010101010101010 "
b1010101010101010 %
