vrtl/Mux4Way16.v
/*  Mux4Way16: 4-way 16-bit multiplexor

 
out =   a if sel == 00
        b if sel == 01
        c if sel == 10
        d if sel == 11


Mux4Way16 u_Mux4Way16(
    .a_i(),
    .b_i(),
    .c_i(),
    .d_i(),
    .sel_i(),
    .out_o()
);

*/

module Mux4Way16(
    input wire [15:0] a_i,
    input wire [15:0] b_i,
    input wire [15:0] c_i,
    input wire [15:0] d_i,
    input wire [1:0] sel_i,
    output wire [15:0] out_o
);
    assign out_o = sel_i[0] ? (sel_i[1] ? d_i : b_i) : (sel_i[1] ? c_i : a_i);

endmodule

vtest/tb/Mux4Way16_tb.v
`timescale 1ns / 1ps

module Mux4Way16_tb();

    reg [15:0] a;
    reg [15:0] b;
    reg [15:0] c;
    reg [15:0] d;
    reg [1:0] sel;
    wire [15:0] out;

    Mux4Way16 u_Mux4Way16(
        .a_i(a),
        .b_i(b),
        .c_i(c),
        .d_i(d),
        .sel_i(sel),
        .out_o(out)
    );

    initial begin
        a = 16'b0000_0000_0000_0000;b = 16'b0000_0000_0000_0000;
        c = 16'b0000_0000_0000_0000;d = 16'b0000_0000_0000_0000;
        sel = 2'b00;
        $display("test running...");
        #10
        a = 16'b0000_0000_0000_0000;b = 16'b0000_0000_0000_0000;
        c = 16'b0000_0000_0000_0000;d = 16'b0000_0000_0000_0000;
        sel = 2'b00;
        #10
        a = 16'b0000_0000_0000_0000;b = 16'b0000_0000_0000_0000;
        c = 16'b0000_0000_0000_0000;d = 16'b0000_0000_0000_0000;
        sel = 2'b01;
        #10
        a = 16'b0000_0000_0000_0000;b = 16'b0000_0000_0000_0000;
        c = 16'b0000_0000_0000_0000;d = 16'b0000_0000_0000_0000;
        sel = 2'b10;
        #10
        a = 16'b0000_0000_0000_0000;b = 16'b0000_0000_0000_0000;
        c = 16'b0000_0000_0000_0000;d = 16'b0000_0000_0000_0000;
        sel = 2'b11;
        #10
        a = 16'b0001001000110100;b = 16'b1001100001110110;
        c = 16'b1010101010101010;d = 16'b0101010101010101;
        sel = 2'b00;
        #10
        a = 16'b0001001000110100;b = 16'b1001100001110110;
        c = 16'b1010101010101010;d = 16'b0101010101010101;
        sel = 2'b01;
        #10
        a = 16'b0001001000110100;b = 16'b1001100001110110;
        c = 16'b1010101010101010;d = 16'b0101010101010101;
        sel = 2'b10;
        #10
        a = 16'b0001001000110100;b = 16'b1001100001110110;
        c = 16'b1010101010101010;d = 16'b0101010101010101;
        sel = 2'b11;
        #1000 
        $finish;
    end

    initial begin
        $dumpfile("vtest/dumpfile/Mux4Way16.vcd");
	    $dumpvars(0,Mux4Way16_tb);
	end

endmodule

vtest/dumpfile/Mux4Way16.vcd
$date
	Mon May  1 12:47:44 2023
$end
$version
	Icarus Verilog
$end
$timescale
	1ps
$end
$scope module Mux4Way16_tb $end
$var wire 16 ! out [15:0] $end
$var reg 16 " a [15:0] $end
$var reg 16 # b [15:0] $end
$var reg 16 $ c [15:0] $end
$var reg 16 % d [15:0] $end
$var reg 2 & sel [1:0] $end
$scope module u_Mux4Way16 $end
$var wire 16 ' a_i [15:0] $end
$var wire 16 ( b_i [15:0] $end
$var wire 16 ) c_i [15:0] $end
$var wire 16 * d_i [15:0] $end
$var wire 2 + sel_i [1:0] $end
$var wire 16 , out_o [15:0] $end
$upscope $end
$upscope $end
$enddefinitions $end
#0
$dumpvars
b0 ,
b0 +
b0 *
b0 )
b0 (
b0 '
b0 &
b0 %
b0 $
b0 #
b0 "
b0 !
$end
#20000
b1 &
b1 +
#30000
b10 &
b10 +
#40000
b11 &
b11 +
#50000
b1001000110100 !
b1001000110100 ,
b0 &
b0 +
b101010101010101 %
b101010101010101 *
b1010101010101010 $
b1010101010101010 )
b1001100001110110 #
b1001100001110110 (
b1001000110100 "
b1001000110100 '
#60000
b1001100001110110 !
b1001100001110110 ,
b1 &
b1 +
#70000
b1010101010101010 !
b1010101010101010 ,
b10 &
b10 +
#80000
b101010101010101 !
b101010101010101 ,
b11 &
b11 +
