vrtl/Mux16.v
/*  Mux16: 16-bit Mux

Mux16 u_Mux16(
    .a_i(),
    .b_i(),
    .sel_i(),
    .out_o()
);

*/

module Mux16(
    input wire [15:0] a_i,
    input wire [15:0] b_i,
    input wire sel_i,
    output wire [15:0] out_o
);
    assign out_o = sel_i ? b_i : a_i;

endmodule

vrtl/Mux4Way16.v
/*  Mux4Way16: 4-way 16-bit multiplexor

 
out =   a if sel == 00
        b if sel == 01
        c if sel == 10
        d if sel == 11


Mux4Way16 u_Mux4Way16(
    .a_i(),
    .b_i(),
    .c_i(),
    .d_i(),
    .sel_i(),
    .out_o()
);

*/

module Mux4Way16(
    input wire [15:0] a_i,
    input wire [15:0] b_i,
    input wire [15:0] c_i,
    input wire [15:0] d_i,
    input wire [1:0] sel_i,
    output wire [15:0] out_o
);
    assign out_o = sel_i[0] ? (sel_i[1] ? d_i : b_i) : (sel_i[1] ? c_i : a_i);

endmodule

vrtl/Mux8Way16.v
/*  Mux8Way16: 8-way 16-bit multiplexor

 
 * out = a if sel == 000
 *       b if sel == 001
 *       etc.
 *       h if sel == 111


Mux8Way16 u_Mux8Way16(
    .a_i(),
    .b_i(),
    .c_i(),
    .d_i(),
    .e_i(),
    .f_i(),
    .g_i(),
    .h_i(),
    .sel_i(),
    .out_o()
);

*/

`include "./Mux4Way16.v"
`include "./Mux16.v"

module Mux8Way16(
    input wire [15:0] a_i,
    input wire [15:0] b_i,
    input wire [15:0] c_i,
    input wire [15:0] d_i,
    input wire [15:0] e_i,
    input wire [15:0] f_i,
    input wire [15:0] g_i,
    input wire [15:0] h_i,
    input wire [2:0] sel_i,
    output wire [15:0] out_o
);

    wire [15:0] tmp1;
    wire [15:0] tmp2;

    Mux4Way16 u1_Mux4Way16(
        .a_i(a_i),
        .b_i(b_i),
        .c_i(c_i),
        .d_i(d_i),
        .sel_i(sel_i[1:0]),
        .out_o(tmp1)
    );
    
    Mux4Way16 u2_Mux4Way16(
        .a_i(e_i),
        .b_i(f_i),
        .c_i(g_i),
        .d_i(h_i),
        .sel_i(sel_i[1:0]),
        .out_o(tmp2)
    );

    Mux16 u_Mux16(
        .a_i(tmp1),
        .b_i(tmp2),
        .sel_i(sel_i[2]),
        .out_o(out_o)
    );
    
endmodule

vtest/Mux8Way16_tb.v
`timescale 1ns / 1ps

module Mux8Way16_tb();

    reg [15:0] a;
    reg [15:0] b;
    reg [15:0] c;
    reg [15:0] d;
    reg [15:0] e;
    reg [15:0] f;
    reg [15:0] g;
    reg [15:0] h;
    reg [2:0] sel;
    wire [15:0] out;

    Mux8Way16 u_Mux8Way16(
        .a_i(a),
        .b_i(b),
        .c_i(c),
        .d_i(d),
        .e_i(e),
        .f_i(f),
        .g_i(g),
        .h_i(h),
        .sel_i(sel),
        .out_o(out)
    );

    initial begin
        a = 16'b0000_0000_0000_0000;b = 16'b0000_0000_0000_0000;
        c = 16'b0000_0000_0000_0000;d = 16'b0000_0000_0000_0000;
        e = 16'b0000_0000_0000_0000;f = 16'b0000_0000_0000_0000;
        g = 16'b0000_0000_0000_0000;h = 16'b0000_0000_0000_0000;
        sel = 3'b000;
        $display("test running...");
        #10
        a = 16'b0000_0000_0000_0000;b = 16'b0000_0000_0000_0000;
        c = 16'b0000_0000_0000_0000;d = 16'b0000_0000_0000_0000;
        e = 16'b0000_0000_0000_0000;f = 16'b0000_0000_0000_0000;
        g = 16'b0000_0000_0000_0000;h = 16'b0000_0000_0000_0000;
        sel = 3'b000;
        #10 sel = 3'b001;
        #10 sel = 3'b010;
        #10 sel = 3'b011;
        #10 sel = 3'b100;
        #10 sel = 3'b101;
        #10 sel = 3'b110;
        #10 sel = 3'b111;
        #10
        a = 16'b0001001000110100;b = 16'b0010001101000101;
        c = 16'b0011010001010110;d = 16'b0100010101100111;
        e = 16'b0101011001111000;f = 16'b0110011110001001;
        g = 16'b0111100010011010;h = 16'b1000100110101011;
        sel = 3'b000;
        #10 sel = 3'b001;
        #10 sel = 3'b010;
        #10 sel = 3'b011;
        #10 sel = 3'b100;
        #10 sel = 3'b101;
        #10 sel = 3'b110;
        #10 sel = 3'b111;
        #1000 
        $finish;
    end

    initial begin
        $dumpfile("vtest/dumpfile/Mux8Way16.vcd");
	    $dumpvars(0,Mux8Way16_tb);
	end

endmodule

vtest/dumpfile/Mux8Way16.vcd
$date
	Mon May  1 12:56:40 2023
$end
$version
	Icarus Verilog
$end
$timescale
	1ps
$end
$scope module Mux8Way16_tb $end
$var wire 16 ! out [15:0] $end
$var reg 16 " a [15:0] $end
$var reg 16 # b [15:0] $end
$var reg 16 $ c [15:0] $end
$var reg 16 % d [15:0] $end
$var reg 16 & e [15:0] $end
$var reg 16 ' f [15:0] $end
$var reg 16 ( g [15:0] $end
$var reg 16 ) h [15:0] $end
$var reg 3 * sel [2:0] $end
$scope module u_Mux8Way16 $end
$var wire 16 + a_i [15:0] $end
$var wire 16 , b_i [15:0] $end
$var wire 16 - c_i [15:0] $end
$var wire 16 . d_i [15:0] $end
$var wire 16 / e_i [15:0] $end
$var wire 16 0 f_i [15:0] $end
$var wire 16 1 g_i [15:0] $end
$var wire 16 2 h_i [15:0] $end
$var wire 3 3 sel_i [2:0] $end
$var wire 16 4 tmp2 [15:0] $end
$var wire 16 5 tmp1 [15:0] $end
$var wire 16 6 out_o [15:0] $end
$scope module u1_Mux4Way16 $end
$var wire 16 7 a_i [15:0] $end
$var wire 16 8 b_i [15:0] $end
$var wire 16 9 c_i [15:0] $end
$var wire 16 : d_i [15:0] $end
$var wire 2 ; sel_i [1:0] $end
$var wire 16 < out_o [15:0] $end
$upscope $end
$scope module u2_Mux4Way16 $end
$var wire 16 = a_i [15:0] $end
$var wire 16 > b_i [15:0] $end
$var wire 16 ? c_i [15:0] $end
$var wire 16 @ d_i [15:0] $end
$var wire 2 A sel_i [1:0] $end
$var wire 16 B out_o [15:0] $end
$upscope $end
$scope module u_Mux16 $end
$var wire 16 C a_i [15:0] $end
$var wire 16 D b_i [15:0] $end
$var wire 1 E sel_i $end
$var wire 16 F out_o [15:0] $end
$upscope $end
$upscope $end
$upscope $end
$enddefinitions $end
#0
$dumpvars
b0 F
0E
b0 D
b0 C
b0 B
b0 A
b0 @
b0 ?
b0 >
b0 =
b0 <
b0 ;
b0 :
b0 9
b0 8
b0 7
b0 6
b0 5
b0 4
b0 3
b0 2
b0 1
b0 0
b0 /
b0 .
b0 -
b0 ,
b0 +
b0 *
b0 )
b0 (
b0 '
b0 &
b0 %
b0 $
b0 #
b0 "
b0 !
$end
#20000
b1 ;
b1 A
b1 *
b1 3
#30000
b10 ;
b10 A
b10 *
b10 3
#40000
b11 ;
b11 A
b11 *
b11 3
#50000
b0 ;
b0 A
1E
b100 *
b100 3
#60000
b1 ;
b1 A
b101 *
b101 3
#70000
b10 ;
b10 A
b110 *
b110 3
#80000
b11 ;
b11 A
b111 *
b111 3
#90000
b1001000110100 !
b1001000110100 6
b1001000110100 F
b101011001111000 4
b101011001111000 B
b101011001111000 D
b1001000110100 5
b1001000110100 <
b1001000110100 C
b0 ;
b0 A
0E
b0 *
b0 3
b1000100110101011 )
b1000100110101011 2
b1000100110101011 @
b111100010011010 (
b111100010011010 1
b111100010011010 ?
b110011110001001 '
b110011110001001 0
b110011110001001 >
b101011001111000 &
b101011001111000 /
b101011001111000 =
b100010101100111 %
b100010101100111 .
b100010101100111 :
b11010001010110 $
b11010001010110 -
b11010001010110 9
b10001101000101 #
b10001101000101 ,
b10001101000101 8
b1001000110100 "
b1001000110100 +
b1001000110100 7
#100000
b10001101000101 !
b10001101000101 6
b10001101000101 F
b10001101000101 5
b10001101000101 <
b10001101000101 C
b110011110001001 4
b110011110001001 B
b110011110001001 D
b1 ;
b1 A
b1 *
b1 3
#110000
b11010001010110 !
b11010001010110 6
b11010001010110 F
b11010001010110 5
b11010001010110 <
b11010001010110 C
b111100010011010 4
b111100010011010 B
b111100010011010 D
b10 ;
b10 A
b10 *
b10 3
#120000
b100010101100111 !
b100010101100111 6
b100010101100111 F
b100010101100111 5
b100010101100111 <
b100010101100111 C
b1000100110101011 4
b1000100110101011 B
b1000100110101011 D
b11 ;
b11 A
b11 *
b11 3
#130000
b1001000110100 5
b1001000110100 <
b1001000110100 C
b101011001111000 4
b101011001111000 B
b101011001111000 D
b101011001111000 !
b101011001111000 6
b101011001111000 F
b0 ;
b0 A
1E
b100 *
b100 3
#140000
b110011110001001 !
b110011110001001 6
b110011110001001 F
b10001101000101 5
b10001101000101 <
b10001101000101 C
b110011110001001 4
b110011110001001 B
b110011110001001 D
b1 ;
b1 A
b101 *
b101 3
#150000
b111100010011010 !
b111100010011010 6
b111100010011010 F
b11010001010110 5
b11010001010110 <
b11010001010110 C
b111100010011010 4
b111100010011010 B
b111100010011010 D
b10 ;
b10 A
b110 *
b110 3
#160000
b1000100110101011 !
b1000100110101011 6
b1000100110101011 F
b100010101100111 5
b100010101100111 <
b100010101100111 C
b1000100110101011 4
b1000100110101011 B
b1000100110101011 D
b11 ;
b11 A
b111 *
b111 3
