vrtl/DFF.v
/*  Data flip-flop gate

DFF u_DFF(
    .clk_i(),
    .in_i(),
    .out_o()
);

*/



module DFF(
    input wire clk_i,
    input wire in_i,
    output reg out_o
);
    always @(posedge clk_i) begin
        out_o <= in_i;
    end

endmodule

vrtl/Bit.v
/*  1-bit register

Bit u_Bit(
    .clk_i(),
    .in_i(),
    .load_i(),
    .out_o()
);

*/



module Bit(
    input wire clk_i,
    input wire in_i,
    input wire load_i,
    output wire out_o
);

    wire in_new = load_i ? in_i : out_o;
    
    DFF u_DFF(
        .clk_i(clk_i),
        .in_i(in_new),
        .out_o(out_o)
    );

endmodule

vrtl/Register.v
/*  16-bit register

Register u_Register(
    .clk_i(),
    .in_i(),
    .load_i(),
    .out_o()
);

*/



module Register(
    input wire clk_i,
    input wire [15:0] in_i,
    input wire load_i,
    output wire [15:0] out_o
);

    Bit u1_Bit(.clk_i(clk_i), .in_i(in_i[0]), .load_i(load_i), .out_o(out_o[0]));
    Bit u2_Bit(.clk_i(clk_i), .in_i(in_i[1]), .load_i(load_i), .out_o(out_o[1]));
    Bit u3_Bit(.clk_i(clk_i), .in_i(in_i[2]), .load_i(load_i), .out_o(out_o[2]));
    Bit u4_Bit(.clk_i(clk_i), .in_i(in_i[3]), .load_i(load_i), .out_o(out_o[3]));
    Bit u5_Bit(.clk_i(clk_i), .in_i(in_i[4]), .load_i(load_i), .out_o(out_o[4]));
    Bit u6_Bit(.clk_i(clk_i), .in_i(in_i[5]), .load_i(load_i), .out_o(out_o[5]));
    Bit u7_Bit(.clk_i(clk_i), .in_i(in_i[6]), .load_i(load_i), .out_o(out_o[6]));
    Bit u8_Bit(.clk_i(clk_i), .in_i(in_i[7]), .load_i(load_i), .out_o(out_o[7]));
    Bit u9_Bit(.clk_i(clk_i), .in_i(in_i[8]), .load_i(load_i), .out_o(out_o[8]));
    Bit u10_Bit(.clk_i(clk_i), .in_i(in_i[9]), .load_i(load_i), .out_o(out_o[9]));
    Bit u11_Bit(.clk_i(clk_i), .in_i(in_i[10]), .load_i(load_i), .out_o(out_o[10]));
    Bit u12_Bit(.clk_i(clk_i), .in_i(in_i[11]), .load_i(load_i), .out_o(out_o[11]));
    Bit u13_Bit(.clk_i(clk_i), .in_i(in_i[12]), .load_i(load_i), .out_o(out_o[12]));
    Bit u14_Bit(.clk_i(clk_i), .in_i(in_i[13]), .load_i(load_i), .out_o(out_o[13]));
    Bit u15_Bit(.clk_i(clk_i), .in_i(in_i[14]), .load_i(load_i), .out_o(out_o[14]));
    Bit u16_Bit(.clk_i(clk_i), .in_i(in_i[15]), .load_i(load_i), .out_o(out_o[15]));

endmodule

vtest/Register_tb.v
`timescale 1ns / 1ps

module Register_tb();

    reg clk;
    reg [15:0] din;
    reg load;
    wire [15:0] dout;

    Register u_Register(
        .clk_i(clk),
        .in_i(din),
        .load_i(load),
        .out_o(dout)
    );

    always #5 clk = ~clk;

    initial begin
        clk = 1'b0; din = 16'b0; load = 1'b1;
        $display("test running...");
        #3 din = -32123;
        #3 din = -32123;
        #3 din = -32123;
        #3 din = 11111;
        #3 din = 11111;
        #3 din = 11111;
        #3 din = 11111;
        #3 din = 12345;
        #3 din = 12345;
        #3 din = 12345;
        #3 din = 8;
        #3 din = 8;
        #3 din = 8;
        #3 din = 32767;
        #3 din = 32767;
        #3 din = 32767;
        #3 din = 1'b1; load = 1'b0;
        #3 din = 1'b1;
        #3 din = 1'b1;
        #3 din = 1'b0;
        #3 din = 1'b0;
        #3 din = 1'b0;
        #3 din = 1'b0;
        #3 din = 1'b1; load = 1'b1;
        #3 din = -16385;
        #3 din = -16385;
        #3 din = -16385;
        #3 din = -16385;
        #3 din = 0;
        #3 din = 0; 
        #3 din = -4097;
        #3 din = -4097;
        #3 din = -4097;
        #3 din = -4097;
        #3 din = -257;
        #3 din = -257;
        #3 din = -257;
        #3 din = -257;
        #3 din = -2;
        #3 din = -2;
        #3 din = -2;
        #3 din = -2;
        #1000 
        $finish;
    end

    initial begin
        $dumpfile("vtest/dumpfile/Register.vcd");
	    $dumpvars(0,Register_tb);
	end

endmodule

vtest/dumpfile/Register.vcd
$date
	Tue May  2 18:36:23 2023
$end
$version
	Icarus Verilog
$end
$timescale
	1ps
$end
$scope module Register_tb $end
$var wire 16 ! dout [15:0] $end
$var reg 1 " clk $end
$var reg 16 # din [15:0] $end
$var reg 1 $ load $end
$scope module u_Register $end
$var wire 1 " clk_i $end
$var wire 16 % in_i [15:0] $end
$var wire 1 $ load_i $end
$var wire 16 & out_o [15:0] $end
$scope module u10_Bit $end
$var wire 1 " clk_i $end
$var wire 1 ' in_i $end
$var wire 1 $ load_i $end
$var wire 1 ( out_o $end
$var wire 1 ) in_new $end
$scope module u_DFF $end
$var wire 1 " clk_i $end
$var wire 1 ) in_i $end
$var reg 1 ( out_o $end
$upscope $end
$upscope $end
$scope module u11_Bit $end
$var wire 1 " clk_i $end
$var wire 1 * in_i $end
$var wire 1 $ load_i $end
$var wire 1 + out_o $end
$var wire 1 , in_new $end
$scope module u_DFF $end
$var wire 1 " clk_i $end
$var wire 1 , in_i $end
$var reg 1 + out_o $end
$upscope $end
$upscope $end
$scope module u12_Bit $end
$var wire 1 " clk_i $end
$var wire 1 - in_i $end
$var wire 1 $ load_i $end
$var wire 1 . out_o $end
$var wire 1 / in_new $end
$scope module u_DFF $end
$var wire 1 " clk_i $end
$var wire 1 / in_i $end
$var reg 1 . out_o $end
$upscope $end
$upscope $end
$scope module u13_Bit $end
$var wire 1 " clk_i $end
$var wire 1 0 in_i $end
$var wire 1 $ load_i $end
$var wire 1 1 out_o $end
$var wire 1 2 in_new $end
$scope module u_DFF $end
$var wire 1 " clk_i $end
$var wire 1 2 in_i $end
$var reg 1 1 out_o $end
$upscope $end
$upscope $end
$scope module u14_Bit $end
$var wire 1 " clk_i $end
$var wire 1 3 in_i $end
$var wire 1 $ load_i $end
$var wire 1 4 out_o $end
$var wire 1 5 in_new $end
$scope module u_DFF $end
$var wire 1 " clk_i $end
$var wire 1 5 in_i $end
$var reg 1 4 out_o $end
$upscope $end
$upscope $end
$scope module u15_Bit $end
$var wire 1 " clk_i $end
$var wire 1 6 in_i $end
$var wire 1 $ load_i $end
$var wire 1 7 out_o $end
$var wire 1 8 in_new $end
$scope module u_DFF $end
$var wire 1 " clk_i $end
$var wire 1 8 in_i $end
$var reg 1 7 out_o $end
$upscope $end
$upscope $end
$scope module u16_Bit $end
$var wire 1 " clk_i $end
$var wire 1 9 in_i $end
$var wire 1 $ load_i $end
$var wire 1 : out_o $end
$var wire 1 ; in_new $end
$scope module u_DFF $end
$var wire 1 " clk_i $end
$var wire 1 ; in_i $end
$var reg 1 : out_o $end
$upscope $end
$upscope $end
$scope module u1_Bit $end
$var wire 1 " clk_i $end
$var wire 1 < in_i $end
$var wire 1 $ load_i $end
$var wire 1 = out_o $end
$var wire 1 > in_new $end
$scope module u_DFF $end
$var wire 1 " clk_i $end
$var wire 1 > in_i $end
$var reg 1 = out_o $end
$upscope $end
$upscope $end
$scope module u2_Bit $end
$var wire 1 " clk_i $end
$var wire 1 ? in_i $end
$var wire 1 $ load_i $end
$var wire 1 @ out_o $end
$var wire 1 A in_new $end
$scope module u_DFF $end
$var wire 1 " clk_i $end
$var wire 1 A in_i $end
$var reg 1 @ out_o $end
$upscope $end
$upscope $end
$scope module u3_Bit $end
$var wire 1 " clk_i $end
$var wire 1 B in_i $end
$var wire 1 $ load_i $end
$var wire 1 C out_o $end
$var wire 1 D in_new $end
$scope module u_DFF $end
$var wire 1 " clk_i $end
$var wire 1 D in_i $end
$var reg 1 C out_o $end
$upscope $end
$upscope $end
$scope module u4_Bit $end
$var wire 1 " clk_i $end
$var wire 1 E in_i $end
$var wire 1 $ load_i $end
$var wire 1 F out_o $end
$var wire 1 G in_new $end
$scope module u_DFF $end
$var wire 1 " clk_i $end
$var wire 1 G in_i $end
$var reg 1 F out_o $end
$upscope $end
$upscope $end
$scope module u5_Bit $end
$var wire 1 " clk_i $end
$var wire 1 H in_i $end
$var wire 1 $ load_i $end
$var wire 1 I out_o $end
$var wire 1 J in_new $end
$scope module u_DFF $end
$var wire 1 " clk_i $end
$var wire 1 J in_i $end
$var reg 1 I out_o $end
$upscope $end
$upscope $end
$scope module u6_Bit $end
$var wire 1 " clk_i $end
$var wire 1 K in_i $end
$var wire 1 $ load_i $end
$var wire 1 L out_o $end
$var wire 1 M in_new $end
$scope module u_DFF $end
$var wire 1 " clk_i $end
$var wire 1 M in_i $end
$var reg 1 L out_o $end
$upscope $end
$upscope $end
$scope module u7_Bit $end
$var wire 1 " clk_i $end
$var wire 1 N in_i $end
$var wire 1 $ load_i $end
$var wire 1 O out_o $end
$var wire 1 P in_new $end
$scope module u_DFF $end
$var wire 1 " clk_i $end
$var wire 1 P in_i $end
$var reg 1 O out_o $end
$upscope $end
$upscope $end
$scope module u8_Bit $end
$var wire 1 " clk_i $end
$var wire 1 Q in_i $end
$var wire 1 $ load_i $end
$var wire 1 R out_o $end
$var wire 1 S in_new $end
$scope module u_DFF $end
$var wire 1 " clk_i $end
$var wire 1 S in_i $end
$var reg 1 R out_o $end
$upscope $end
$upscope $end
$scope module u9_Bit $end
$var wire 1 " clk_i $end
$var wire 1 T in_i $end
$var wire 1 $ load_i $end
$var wire 1 U out_o $end
$var wire 1 V in_new $end
$scope module u_DFF $end
$var wire 1 " clk_i $end
$var wire 1 V in_i $end
$var reg 1 U out_o $end
$upscope $end
$upscope $end
$upscope $end
$upscope $end
$enddefinitions $end
#0
$dumpvars
0V
xU
0T
0S
xR
0Q
0P
xO
0N
0M
xL
0K
0J
xI
0H
0G
xF
0E
0D
xC
0B
0A
x@
0?
0>
x=
0<
0;
x:
09
08
x7
06
05
x4
03
02
x1
00
0/
x.
0-
0,
x+
0*
0)
x(
0'
bx &
b0 %
1$
b0 #
0"
bx !
$end
#3000
1>
1D
1S
1)
1;
1<
1B
1Q
1'
19
b1000001010000101 #
b1000001010000101 %
#5000
1=
0@
1C
0F
0I
0L
0O
1R
0U
1(
0+
0.
01
04
07
b1000001010000101 !
b1000001010000101 &
1:
1"
#10000
0"
#12000
1A
1M
1P
0S
1V
1/
15
0;
1?
1K
1N
0Q
1T
1-
13
09
b10101101100111 #
b10101101100111 %
#15000
0:
14
1.
1U
0R
1O
1L
b10101101100111 !
b10101101100111 &
1@
1"
#20000
0"
#24000
0A
0D
1G
1J
0P
0V
0)
0/
12
0?
0B
1E
1H
0N
0T
0'
0-
10
b11000000111001 #
b11000000111001 %
#25000
0@
0C
1F
1I
0O
0U
0(
0.
b11000000111001 !
b11000000111001 &
11
1"
#30000
0"
#33000
0>
0J
0M
02
05
0<
0H
0K
00
03
b1000 #
b1000 %
#35000
04
01
0L
0I
b1000 !
b1000 &
0=
1"
#40000
0"
#42000
1>
1A
1D
1J
1M
1P
1S
1V
1)
1,
1/
12
15
18
1<
1?
1B
1H
1K
1N
1Q
1T
1'
1*
1-
10
13
16
b111111111111111 #
b111111111111111 %
#45000
1=
1@
1C
1I
1L
1O
1R
1U
1(
1+
1.
11
14
b111111111111111 !
b111111111111111 &
17
1"
#50000
0"
#51000
0?
0B
0E
0H
0K
0N
0Q
0T
0'
0*
0-
00
03
06
0$
b1 #
b1 %
#55000
1"
#60000
0<
b0 #
b0 %
0"
#65000
1"
#70000
0"
#72000
0)
0,
0/
02
05
08
0A
0D
0G
0J
0M
0P
0S
0V
1<
1$
b1 #
b1 %
#75000
07
04
01
0.
0+
0(
0U
0R
0O
0L
0I
0F
0C
b1 !
b1 &
0@
1A
1D
1G
1J
1M
1P
1S
1V
1)
1,
1/
12
15
1;
1?
1B
1E
1H
1K
1N
1Q
1T
1'
1*
1-
10
13
19
b1011111111111111 #
b1011111111111111 %
1"
#80000
0"
#85000
1@
1C
1F
1I
1L
1O
1R
1U
1(
1+
1.
11
14
b1011111111111111 !
b1011111111111111 &
1:
1"
#87000
0>
0A
0D
0G
0J
0M
0P
0S
0V
0)
0,
0/
02
05
0;
0<
0?
0B
0E
0H
0K
0N
0Q
0T
0'
0*
0-
00
03
09
b0 #
b0 %
#90000
0"
#93000
1>
1A
1D
1G
1J
1M
1P
1S
1V
1)
1,
1/
15
18
1;
1<
1?
1B
1E
1H
1K
1N
1Q
1T
1'
1*
1-
13
16
19
b1110111111111111 #
b1110111111111111 %
#95000
17
b1110111111111111 !
b1110111111111111 &
01
1"
#100000
0"
#105000
0V
12
0T
10
b1111111011111111 #
b1111111011111111 %
1"
#110000
0"
#115000
11
b1111111011111111 !
b1111111011111111 &
0U
1"
#117000
0>
1V
0<
1T
b1111111111111110 #
b1111111111111110 %
#120000
0"
#125000
0=
b1111111111111110 !
b1111111111111110 &
1U
1"
